[
  {
    "FixtureId": 18241006,
    "GameState": "scheduled",
    "StartTime": 1784142000000,
    "IsTeam": true,
    "FixtureGroupId": 10115573,
    "CompetitionId": 72,
    "CountryId": 466,
    "SportId": 1,
    "Participant1IsHome": true,
    "Participant2Id": 1489,
    "Participant1Id": 1888,
    "CoverageSecondaryData": true,
    "CoverageType": "TV/Stream",
    "Action": "action_amend",
    "Id": 749,
    "Ts": 1784148699018,
    "ConnectionId": 1129,
    "Seq": 854,
    "StatusId": 4,
    "Type": "Soccer",
    "Clock": {
      "Running": true,
      "Seconds": 5430
    },
    "Score": {
      "Participant1": {
        "H1": {
          "YellowCards": 1,
          "Corners": 1
        },
        "HT": {
          "YellowCards": 1,
          "Corners": 1
        },
        "H2": {
          "Goals": 1
        },
        "Total": {
          "Goals": 1,
          "YellowCards": 1,
          "Corners": 1
        }
      },
      "Participant2": {
        "H1": {
          "YellowCards": 1,
          "Corners": 1
        },
        "HT": {
          "YellowCards": 1,
          "Corners": 1
        },
        "H2": {
          "Goals": 1,
          "YellowCards": 1,
          "Corners": 5
        },
        "Total": {
          "Goals": 1,
          "YellowCards": 2,
          "Corners": 6
        }
      }
    },
    "Data": {
      "Action": "injury",
      "New": {
        "Clock": {
          "Running": true,
          "Seconds": 5284
        },
        "Outcome": "OnPitch",
        "PlayerId": 162605
      },
      "Previous": {
        "Clock": {
          "Running": true,
          "Seconds": 5284
        },
        "Outcome": "OffPitch",
        "PlayerId": 162605
      }
    },
    "Stats": {
      "1": 1,
      "2": 1,
      "3": 1,
      "4": 2,
      "5": 0,
      "6": 0,
      "7": 1,
      "8": 6,
      "1001": 0,
      "1002": 0,
      "1003": 1,
      "1004": 1,
      "1005": 0,
      "1006": 0,
      "1007": 1,
      "1008": 1,
      "2001": 0,
      "2002": 0,
      "2003": 1,
      "2004": 1,
      "2005": 0,
      "2006": 0,
      "2007": 1,
      "2008": 1,
      "3001": 1,
      "3002": 1,
      "3003": 0,
      "3004": 1,
      "3005": 0,
      "3006": 0,
      "3007": 0,
      "3008": 5,
      "4001": 0,
      "4002": 0,
      "4003": 0,
      "4004": 0,
      "4005": 0,
      "4006": 0,
      "4007": 0,
      "4008": 0,
      "5001": 0,
      "5002": 0,
      "5003": 0,
      "5004": 0,
      "5005": 0,
      "5006": 0,
      "5007": 0,
      "5008": 0,
      "6001": 0,
      "6002": 0,
      "6003": 0,
      "6004": 0,
      "6005": 0,
      "6006": 0,
      "6007": 0,
      "6008": 0,
      "7001": 0,
      "7002": 0,
      "7003": 0,
      "7004": 0,
      "7005": 0,
      "7006": 0,
      "7007": 0,
      "7008": 0
    },
    "Participant": 1,
    "Possession": 2,
    "PossessionType": "AttackPossession"
  },
  {
    "FixtureId": 18241006,
    "GameState": "scheduled",
    "StartTime": 1784142000000,
    "IsTeam": true,
    "FixtureGroupId": 10115573,
    "CompetitionId": 72,
    "CountryId": 466,
    "SportId": 1,
    "Participant1IsHome": true,
    "Participant2Id": 1489,
    "Participant1Id": 1888,
    "CoverageSecondaryData": true,
    "CoverageType": "TV/Stream",
    "Action": "action_discarded",
    "Id": 373,
    "Ts": 1784144919031,
    "ConnectionId": 1159,
    "Seq": 421,
    "Clock": {
      "Running": true,
      "Seconds": 2888
    },
    "Score": {
      "Participant1": {
        "H1": {
          "YellowCards": 1,
          "Corners": 1
        },
        "HT": {
          "YellowCards": 1,
          "Corners": 1
        },
        "Total": {
          "YellowCards": 1,
          "Corners": 1
        }
      },
      "Participant2": {
        "H1": {
          "YellowCards": 1,
          "Corners": 1
        },
        "HT": {
          "YellowCards": 1,
          "Corners": 1
        },
        "Total": {
          "YellowCards": 1,
          "Corners": 1
        }
      }
    },
    "Data": {},
    "Stats": {
      "1": 0,
      "2": 0,
      "3": 1,
      "4": 1,
      "5": 0,
      "6": 0,
      "7": 1,
      "8": 1,
      "1001": 0,
      "1002": 0,
      "1003": 1,
      "1004": 1,
      "1005": 0,
      "1006": 0,
      "1007": 1,
      "1008": 1,
      "2001": 0,
      "2002": 0,
      "2003": 1,
      "2004": 1,
      "2005": 0,
      "2006": 0,
      "2007": 1,
      "2008": 1,
      "3001": 0,
      "3002": 0,
      "3003": 0,
      "3004": 0,
      "3005": 0,
      "3006": 0,
      "3007": 0,
      "3008": 0,
      "4001": 0,
      "4002": 0,
      "4003": 0,
      "4004": 0,
      "4005": 0,
      "4006": 0,
      "4007": 0,
      "4008": 0,
      "5001": 0,
      "5002": 0,
      "5003": 0,
      "5004": 0,
      "5005": 0,
      "5006": 0,
      "5007": 0,
      "5008": 0,
      "6001": 0,
      "6002": 0,
      "6003": 0,
      "6004": 0,
      "6005": 0,
      "6006": 0,
      "6007": 0,
      "6008": 0,
      "7001": 0,
      "7002": 0,
      "7003": 0,
      "7004": 0,
      "7005": 0,
      "7006": 0,
      "7007": 0,
      "7008": 0
    },
    "Possession": 1,
    "PossessionType": "HighDangerPossession",
    "Parti1State": {},
    "Parti2State": {},
    "PossibleEvent": {}
  },
  {
    "FixtureId": 18241006,
    "GameState": "scheduled",
    "StartTime": 1784142000000,
    "IsTeam": true,
    "FixtureGroupId": 10115573,
    "CompetitionId": 72,
    "CountryId": 466,
    "SportId": 1,
    "Participant1IsHome": true,
    "Participant2Id": 1489,
    "Participant1Id": 1888,
    "CoverageSecondaryData": true,
    "CoverageType": "TV/Stream",
    "Action": "additional_time",
    "Id": 747,
    "Ts": 1784148673813,
    "ConnectionId": 1159,
    "Seq": 852,
    "StatusId": 4,
    "Type": "Soccer",
    "Confirmed": true,
    "Clock": {
      "Running": true,
      "Seconds": 5401
    },
    "Data": {
      "Minutes": 9
    },
    "Stats": {
      "1": 1,
      "2": 1,
      "3": 1,
      "4": 2,
      "5": 0,
      "6": 0,
      "7": 1,
      "8": 6,
      "1001": 0,
      "1002": 0,
      "1003": 1,
      "1004": 1,
      "1005": 0,
      "1006": 0,
      "1007": 1,
      "1008": 1,
      "2001": 0,
      "2002": 0,
      "2003": 1,
      "2004": 1,
      "2005": 0,
      "2006": 0,
      "2007": 1,
      "2008": 1,
      "3001": 1,
      "3002": 1,
      "3003": 0,
      "3004": 1,
      "3005": 0,
      "3006": 0,
      "3007": 0,
      "3008": 5,
      "4001": 0,
      "4002": 0,
      "4003": 0,
      "4004": 0,
      "4005": 0,
      "4006": 0,
      "4007": 0,
      "4008": 0,
      "5001": 0,
      "5002": 0,
      "5003": 0,
      "5004": 0,
      "5005": 0,
      "5006": 0,
      "5007": 0,
      "5008": 0,
      "6001": 0,
      "6002": 0,
      "6003": 0,
      "6004": 0,
      "6005": 0,
      "6006": 0,
      "6007": 0,
      "6008": 0,
      "7001": 0,
      "7002": 0,
      "7003": 0,
      "7004": 0,
      "7005": 0,
      "7006": 0,
      "7007": 0,
      "7008": 0
    }
  },
  {
    "FixtureId": 18241006,
    "GameState": "scheduled",
    "StartTime": 1784142000000,
    "IsTeam": true,
    "FixtureGroupId": 10115573,
    "CompetitionId": 72,
    "CountryId": 466,
    "SportId": 1,
    "Participant1IsHome": true,
    "Participant2Id": 1489,
    "Participant1Id": 1888,
    "CoverageSecondaryData": true,
    "CoverageType": "TV/Stream",
    "Action": "attack_possession",
    "Id": 837,
    "Ts": 1784149371684,
    "ConnectionId": 1159,
    "Seq": 958,
    "StatusId": 4,
    "Type": "Soccer",
    "Clock": {
      "Running": true,
      "Seconds": 6103
    },
    "Stats": {
      "1": 1,
      "2": 2,
      "3": 1,
      "4": 3,
      "5": 0,
      "6": 0,
      "7": 1,
      "8": 6,
      "1001": 0,
      "1002": 0,
      "1003": 1,
      "1004": 1,
      "1005": 0,
      "1006": 0,
      "1007": 1,
      "1008": 1,
      "2001": 0,
      "2002": 0,
      "2003": 1,
      "2004": 1,
      "2005": 0,
      "2006": 0,
      "2007": 1,
      "2008": 1,
      "3001": 1,
      "3002": 2,
      "3003": 0,
      "3004": 2,
      "3005": 0,
      "3006": 0,
      "3007": 0,
      "3008": 5,
      "4001": 0,
      "4002": 0,
      "4003": 0,
      "4004": 0,
      "4005": 0,
      "4006": 0,
      "4007": 0,
      "4008": 0,
      "5001": 0,
      "5002": 0,
      "5003": 0,
      "5004": 0,
      "5005": 0,
      "5006": 0,
      "5007": 0,
      "5008": 0,
      "6001": 0,
      "6002": 0,
      "6003": 0,
      "6004": 0,
      "6005": 0,
      "6006": 0,
      "6007": 0,
      "6008": 0,
      "7001": 0,
      "7002": 0,
      "7003": 0,
      "7004": 0,
      "7005": 0,
      "7006": 0,
      "7007": 0,
      "7008": 0
    },
    "Participant": 2,
    "Possession": 2,
    "PossessionType": "AttackPossession"
  },
  {
    "FixtureId": 18241006,
    "GameState": "scheduled",
    "StartTime": 1784142000000,
    "IsTeam": true,
    "FixtureGroupId": 10115573,
    "CompetitionId": 72,
    "CountryId": 466,
    "SportId": 1,
    "Participant1IsHome": true,
    "Participant2Id": 1489,
    "Participant1Id": 1888,
    "CoverageSecondaryData": true,
    "CoverageType": "TV/Stream",
    "Action": "clock_adjustment",
    "Id": 840,
    "Ts": 1784149378104,
    "ConnectionId": 1129,
    "Seq": 961,
    "StatusId": 5,
    "Type": "Soccer",
    "Clock": {
      "Running": false,
      "Seconds": 0
    },
    "Data": {},
    "Stats": {
      "1": 1,
      "2": 2,
      "3": 1,
      "4": 3,
      "5": 0,
      "6": 0,
      "7": 1,
      "8": 6,
      "1001": 0,
      "1002": 0,
      "1003": 1,
      "1004": 1,
      "1005": 0,
      "1006": 0,
      "1007": 1,
      "1008": 1,
      "2001": 0,
      "2002": 0,
      "2003": 1,
      "2004": 1,
      "2005": 0,
      "2006": 0,
      "2007": 1,
      "2008": 1,
      "3001": 1,
      "3002": 2,
      "3003": 0,
      "3004": 2,
      "3005": 0,
      "3006": 0,
      "3007": 0,
      "3008": 5,
      "4001": 0,
      "4002": 0,
      "4003": 0,
      "4004": 0,
      "4005": 0,
      "4006": 0,
      "4007": 0,
      "4008": 0,
      "5001": 0,
      "5002": 0,
      "5003": 0,
      "5004": 0,
      "5005": 0,
      "5006": 0,
      "5007": 0,
      "5008": 0,
      "6001": 0,
      "6002": 0,
      "6003": 0,
      "6004": 0,
      "6005": 0,
      "6006": 0,
      "6007": 0,
      "6008": 0,
      "7001": 0,
      "7002": 0,
      "7003": 0,
      "7004": 0,
      "7005": 0,
      "7006": 0,
      "7007": 0,
      "7008": 0
    }
  },
  {
    "FixtureId": 18241006,
    "GameState": "scheduled",
    "StartTime": 1784142000000,
    "IsTeam": true,
    "FixtureGroupId": 10115573,
    "CompetitionId": 72,
    "CountryId": 466,
    "SportId": 1,
    "Participant1IsHome": true,
    "Participant2Id": 1489,
    "Participant1Id": 1888,
    "CoverageSecondaryData": true,
    "CoverageType": "TV/Stream",
    "Action": "comment",
    "Id": 662,
    "Ts": 1784147914102,
    "ConnectionId": 1129,
    "Seq": 749,
    "Data": {},
    "Stats": {
      "1": 1,
      "2": 0,
      "3": 1,
      "4": 2,
      "5": 0,
      "6": 0,
      "7": 1,
      "8": 5,
      "1001": 0,
      "1002": 0,
      "1003": 1,
      "1004": 1,
      "1005": 0,
      "1006": 0,
      "1007": 1,
      "1008": 1,
      "2001": 0,
      "2002": 0,
      "2003": 1,
      "2004": 1,
      "2005": 0,
      "2006": 0,
      "2007": 1,
      "2008": 1,
      "3001": 1,
      "3002": 0,
      "3003": 0,
      "3004": 1,
      "3005": 0,
      "3006": 0,
      "3007": 0,
      "3008": 4,
      "4001": 0,
      "4002": 0,
      "4003": 0,
      "4004": 0,
      "4005": 0,
      "4006": 0,
      "4007": 0,
      "4008": 0,
      "5001": 0,
      "5002": 0,
      "5003": 0,
      "5004": 0,
      "5005": 0,
      "5006": 0,
      "5007": 0,
      "5008": 0,
      "6001": 0,
      "6002": 0,
      "6003": 0,
      "6004": 0,
      "6005": 0,
      "6006": 0,
      "6007": 0,
      "6008": 0,
      "7001": 0,
      "7002": 0,
      "7003": 0,
      "7004": 0,
      "7005": 0,
      "7006": 0,
      "7007": 0,
      "7008": 0
    }
  },
  {
    "FixtureId": 18241006,
    "GameState": "scheduled",
    "StartTime": 1784142000000,
    "IsTeam": true,
    "FixtureGroupId": 10115573,
    "CompetitionId": 72,
    "CountryId": 466,
    "SportId": 1,
    "Participant1IsHome": true,
    "Participant2Id": 1489,
    "Participant1Id": 1888,
    "CoverageSecondaryData": true,
    "CoverageType": "TV/Stream",
    "Action": "connected",
    "Id": 2,
    "Ts": 1784139396966,
    "ConnectionId": 1159,
    "Seq": 2,
    "Confirmed": true,
    "Stats": {}
  },
  {
    "FixtureId": 18241006,
    "GameState": "scheduled",
    "StartTime": 1784142000000,
    "IsTeam": true,
    "FixtureGroupId": 10115573,
    "CompetitionId": 72,
    "CountryId": 466,
    "SportId": 1,
    "Participant1IsHome": true,
    "Participant2Id": 1489,
    "Participant1Id": 1888,
    "CoverageSecondaryData": true,
    "CoverageType": "TV/Stream",
    "Action": "corner",
    "Id": 725,
    "Ts": 1784148352217,
    "ConnectionId": 1159,
    "Seq": 824,
    "StatusId": 4,
    "Type": "Soccer",
    "Confirmed": true,
    "Clock": {
      "Running": true,
      "Seconds": 5071
    },
    "Score": {
      "Participant1": {
        "H1": {
          "YellowCards": 1,
          "Corners": 1
        },
        "HT": {
          "YellowCards": 1,
          "Corners": 1
        },
        "H2": {
          "Goals": 1
        },
        "Total": {
          "Goals": 1,
          "YellowCards": 1,
          "Corners": 1
        }
      },
      "Participant2": {
        "H1": {
          "YellowCards": 1,
          "Corners": 1
        },
        "HT": {
          "YellowCards": 1,
          "Corners": 1
        },
        "H2": {
          "YellowCards": 1,
          "Corners": 5
        },
        "Total": {
          "YellowCards": 2,
          "Corners": 6
        }
      }
    },
    "Stats": {
      "1": 1,
      "2": 0,
      "3": 1,
      "4": 2,
      "5": 0,
      "6": 0,
      "7": 1,
      "8": 6,
      "1001": 0,
      "1002": 0,
      "1003": 1,
      "1004": 1,
      "1005": 0,
      "1006": 0,
      "1007": 1,
      "1008": 1,
      "2001": 0,
      "2002": 0,
      "2003": 1,
      "2004": 1,
      "2005": 0,
      "2006": 0,
      "2007": 1,
      "2008": 1,
      "3001": 1,
      "3002": 0,
      "3003": 0,
      "3004": 1,
      "3005": 0,
      "3006": 0,
      "3007": 0,
      "3008": 5,
      "4001": 0,
      "4002": 0,
      "4003": 0,
      "4004": 0,
      "4005": 0,
      "4006": 0,
      "4007": 0,
      "4008": 0,
      "5001": 0,
      "5002": 0,
      "5003": 0,
      "5004": 0,
      "5005": 0,
      "5006": 0,
      "5007": 0,
      "5008": 0,
      "6001": 0,
      "6002": 0,
      "6003": 0,
      "6004": 0,
      "6005": 0,
      "6006": 0,
      "6007": 0,
      "6008": 0,
      "7001": 0,
      "7002": 0,
      "7003": 0,
      "7004": 0,
      "7005": 0,
      "7006": 0,
      "7007": 0,
      "7008": 0
    },
    "Participant": 2,
    "Possession": 2,
    "Parti1State": {},
    "Parti2State": {}
  },
  {
    "FixtureId": 18241006,
    "GameState": "scheduled",
    "StartTime": 1784142000000,
    "IsTeam": true,
    "FixtureGroupId": 10115573,
    "CompetitionId": 72,
    "CountryId": 466,
    "SportId": 1,
    "Participant1IsHome": true,
    "Participant2Id": 1489,
    "Participant1Id": 1888,
    "Action": "coverage_update",
    "Id": 0,
    "Ts": 1783828320792,
    "ConnectionId": 1061,
    "Seq": 0,
    "Data": {},
    "Stats": {}
  },
  {
    "FixtureId": 18241006,
    "GameState": "scheduled",
    "StartTime": 1784142000000,
    "IsTeam": true,
    "FixtureGroupId": 10115573,
    "CompetitionId": 72,
    "CountryId": 466,
    "SportId": 1,
    "Participant1IsHome": true,
    "Participant2Id": 1489,
    "Participant1Id": 1888,
    "CoverageSecondaryData": true,
    "CoverageType": "TV/Stream",
    "Action": "danger_possession",
    "Id": 822,
    "Ts": 1784149260883,
    "ConnectionId": 1159,
    "Seq": 941,
    "StatusId": 4,
    "Type": "Soccer",
    "Clock": {
      "Running": true,
      "Seconds": 5993
    },
    "Stats": {
      "1": 1,
      "2": 2,
      "3": 1,
      "4": 3,
      "5": 0,
      "6": 0,
      "7": 1,
      "8": 6,
      "1001": 0,
      "1002": 0,
      "1003": 1,
      "1004": 1,
      "1005": 0,
      "1006": 0,
      "1007": 1,
      "1008": 1,
      "2001": 0,
      "2002": 0,
      "2003": 1,
      "2004": 1,
      "2005": 0,
      "2006": 0,
      "2007": 1,
      "2008": 1,
      "3001": 1,
      "3002": 2,
      "3003": 0,
      "3004": 2,
      "3005": 0,
      "3006": 0,
      "3007": 0,
      "3008": 5,
      "4001": 0,
      "4002": 0,
      "4003": 0,
      "4004": 0,
      "4005": 0,
      "4006": 0,
      "4007": 0,
      "4008": 0,
      "5001": 0,
      "5002": 0,
      "5003": 0,
      "5004": 0,
      "5005": 0,
      "5006": 0,
      "5007": 0,
      "5008": 0,
      "6001": 0,
      "6002": 0,
      "6003": 0,
      "6004": 0,
      "6005": 0,
      "6006": 0,
      "6007": 0,
      "6008": 0,
      "7001": 0,
      "7002": 0,
      "7003": 0,
      "7004": 0,
      "7005": 0,
      "7006": 0,
      "7007": 0,
      "7008": 0
    },
    "Participant": 2,
    "Possession": 2,
    "PossessionType": "DangerPossession"
  },
  {
    "FixtureId": 18241006,
    "GameState": "scheduled",
    "StartTime": 1784142000000,
    "IsTeam": true,
    "FixtureGroupId": 10115573,
    "CompetitionId": 72,
    "CountryId": 466,
    "SportId": 1,
    "Participant1IsHome": true,
    "Participant2Id": 1489,
    "Participant1Id": 1888,
    "CoverageSecondaryData": true,
    "CoverageType": "TV/Stream",
    "Action": "disconnected",
    "Id": 844,
    "Ts": 1784150592580,
    "ConnectionId": 1129,
    "Seq": 963,
    "Confirmed": true,
    "Stats": {
      "1": 1,
      "2": 2,
      "3": 1,
      "4": 3,
      "5": 0,
      "6": 0,
      "7": 1,
      "8": 6,
      "1001": 0,
      "1002": 0,
      "1003": 1,
      "1004": 1,
      "1005": 0,
      "1006": 0,
      "1007": 1,
      "1008": 1,
      "2001": 0,
      "2002": 0,
      "2003": 1,
      "2004": 1,
      "2005": 0,
      "2006": 0,
      "2007": 1,
      "2008": 1,
      "3001": 1,
      "3002": 2,
      "3003": 0,
      "3004": 2,
      "3005": 0,
      "3006": 0,
      "3007": 0,
      "3008": 5,
      "4001": 0,
      "4002": 0,
      "4003": 0,
      "4004": 0,
      "4005": 0,
      "4006": 0,
      "4007": 0,
      "4008": 0,
      "5001": 0,
      "5002": 0,
      "5003": 0,
      "5004": 0,
      "5005": 0,
      "5006": 0,
      "5007": 0,
      "5008": 0,
      "6001": 0,
      "6002": 0,
      "6003": 0,
      "6004": 0,
      "6005": 0,
      "6006": 0,
      "6007": 0,
      "6008": 0,
      "7001": 0,
      "7002": 0,
      "7003": 0,
      "7004": 0,
      "7005": 0,
      "7006": 0,
      "7007": 0,
      "7008": 0
    }
  },
  {
    "FixtureId": 18241006,
    "GameState": "scheduled",
    "StartTime": 1784142000000,
    "IsTeam": true,
    "FixtureGroupId": 10115573,
    "CompetitionId": 72,
    "CountryId": 466,
    "SportId": 1,
    "Participant1IsHome": true,
    "Participant2Id": 1489,
    "Participant1Id": 1888,
    "CoverageSecondaryData": true,
    "CoverageType": "TV/Stream",
    "Action": "free_kick",
    "Id": 836,
    "Ts": 1784149339781,
    "ConnectionId": 1159,
    "Seq": 957,
    "StatusId": 4,
    "Type": "Soccer",
    "Confirmed": true,
    "Clock": {
      "Running": true,
      "Seconds": 6071
    },
    "Data": {
      "FreeKickType": "Safe"
    },
    "Stats": {
      "1": 1,
      "2": 2,
      "3": 1,
      "4": 3,
      "5": 0,
      "6": 0,
      "7": 1,
      "8": 6,
      "1001": 0,
      "1002": 0,
      "1003": 1,
      "1004": 1,
      "1005": 0,
      "1006": 0,
      "1007": 1,
      "1008": 1,
      "2001": 0,
      "2002": 0,
      "2003": 1,
      "2004": 1,
      "2005": 0,
      "2006": 0,
      "2007": 1,
      "2008": 1,
      "3001": 1,
      "3002": 2,
      "3003": 0,
      "3004": 2,
      "3005": 0,
      "3006": 0,
      "3007": 0,
      "3008": 5,
      "4001": 0,
      "4002": 0,
      "4003": 0,
      "4004": 0,
      "4005": 0,
      "4006": 0,
      "4007": 0,
      "4008": 0,
      "5001": 0,
      "5002": 0,
      "5003": 0,
      "5004": 0,
      "5005": 0,
      "5006": 0,
      "5007": 0,
      "5008": 0,
      "6001": 0,
      "6002": 0,
      "6003": 0,
      "6004": 0,
      "6005": 0,
      "6006": 0,
      "6007": 0,
      "6008": 0,
      "7001": 0,
      "7002": 0,
      "7003": 0,
      "7004": 0,
      "7005": 0,
      "7006": 0,
      "7007": 0,
      "7008": 0
    },
    "Participant": 2,
    "Possession": 2
  },
  {
    "FixtureId": 18241006,
    "GameState": "scheduled",
    "StartTime": 1784142000000,
    "IsTeam": true,
    "FixtureGroupId": 10115573,
    "CompetitionId": 72,
    "CountryId": 466,
    "SportId": 1,
    "Participant1IsHome": true,
    "Participant2Id": 1489,
    "Participant1Id": 1888,
    "CoverageSecondaryData": true,
    "CoverageType": "TV/Stream",
    "Action": "game_finalised",
    "Id": 843,
    "Ts": 1784150064772,
    "ConnectionId": 1140,
    "Seq": 962,
    "StatusId": 100,
    "Score": {
      "Participant1": {
        "H1": {
          "YellowCards": 1,
          "Corners": 1
        },
        "HT": {
          "YellowCards": 1,
          "Corners": 1
        },
        "H2": {
          "Goals": 1
        },
        "Total": {
          "Goals": 1,
          "YellowCards": 1,
          "Corners": 1
        }
      },
      "Participant2": {
        "H1": {
          "YellowCards": 1,
          "Corners": 1
        },
        "HT": {
          "YellowCards": 1,
          "Corners": 1
        },
        "H2": {
          "Goals": 2,
          "YellowCards": 2,
          "Corners": 5
        },
        "Total": {
          "Goals": 2,
          "YellowCards": 3,
          "Corners": 6
        }
      }
    },
    "Stats": {
      "1": 1,
      "2": 2,
      "3": 1,
      "4": 3,
      "5": 0,
      "6": 0,
      "7": 1,
      "8": 6,
      "1001": 0,
      "1002": 0,
      "1003": 1,
      "1004": 1,
      "1005": 0,
      "1006": 0,
      "1007": 1,
      "1008": 1,
      "2001": 0,
      "2002": 0,
      "2003": 1,
      "2004": 1,
      "2005": 0,
      "2006": 0,
      "2007": 1,
      "2008": 1,
      "3001": 1,
      "3002": 2,
      "3003": 0,
      "3004": 2,
      "3005": 0,
      "3006": 0,
      "3007": 0,
      "3008": 5,
      "4001": 0,
      "4002": 0,
      "4003": 0,
      "4004": 0,
      "4005": 0,
      "4006": 0,
      "4007": 0,
      "4008": 0,
      "5001": 0,
      "5002": 0,
      "5003": 0,
      "5004": 0,
      "5005": 0,
      "5006": 0,
      "5007": 0,
      "5008": 0,
      "6001": 0,
      "6002": 0,
      "6003": 0,
      "6004": 0,
      "6005": 0,
      "6006": 0,
      "6007": 0,
      "6008": 0,
      "7001": 0,
      "7002": 0,
      "7003": 0,
      "7004": 0,
      "7005": 0,
      "7006": 0,
      "7007": 0,
      "7008": 0
    },
    "PlayerStats": {
      "Participant1": {
        "911404": {
          "goals": 1
        },
        "10015384": {
          "yellowCards": 1
        }
      },
      "Participant2": {
        "948167": {
          "goals": 1
        },
        "1055356": {
          "yellowCards": 1
        },
        "1103557": {
          "yellowCards": 1
        },
        "10035609": {
          "goals": 1
        },
        "10093937": {
          "yellowCards": 1
        }
      }
    }
  },
  {
    "FixtureId": 18241006,
    "GameState": "scheduled",
    "StartTime": 1784142000000,
    "IsTeam": true,
    "FixtureGroupId": 10115573,
    "CompetitionId": 72,
    "CountryId": 466,
    "SportId": 1,
    "Participant1IsHome": true,
    "Participant2Id": 1489,
    "Participant1Id": 1888,
    "CoverageSecondaryData": true,
    "CoverageType": "TV/Stream",
    "Action": "goal",
    "Id": 764,
    "Ts": 1784148874142,
    "ConnectionId": 1159,
    "Seq": 872,
    "StatusId": 4,
    "Type": "Soccer",
    "Confirmed": true,
    "Clock": {
      "Running": true,
      "Seconds": 5488
    },
    "Score": {
      "Participant1": {
        "H1": {
          "YellowCards": 1,
          "Corners": 1
        },
        "HT": {
          "YellowCards": 1,
          "Corners": 1
        },
        "H2": {
          "Goals": 1
        },
        "Total": {
          "Goals": 1,
          "YellowCards": 1,
          "Corners": 1
        }
      },
      "Participant2": {
        "H1": {
          "YellowCards": 1,
          "Corners": 1
        },
        "HT": {
          "YellowCards": 1,
          "Corners": 1
        },
        "H2": {
          "Goals": 2,
          "YellowCards": 1,
          "Corners": 5
        },
        "Total": {
          "Goals": 2,
          "YellowCards": 2,
          "Corners": 6
        }
      }
    },
    "Data": {
      "GoalType": "Head",
      "PlayerId": 948167
    },
    "Stats": {
      "1": 1,
      "2": 2,
      "3": 1,
      "4": 2,
      "5": 0,
      "6": 0,
      "7": 1,
      "8": 6,
      "1001": 0,
      "1002": 0,
      "1003": 1,
      "1004": 1,
      "1005": 0,
      "1006": 0,
      "1007": 1,
      "1008": 1,
      "2001": 0,
      "2002": 0,
      "2003": 1,
      "2004": 1,
      "2005": 0,
      "2006": 0,
      "2007": 1,
      "2008": 1,
      "3001": 1,
      "3002": 2,
      "3003": 0,
      "3004": 1,
      "3005": 0,
      "3006": 0,
      "3007": 0,
      "3008": 5,
      "4001": 0,
      "4002": 0,
      "4003": 0,
      "4004": 0,
      "4005": 0,
      "4006": 0,
      "4007": 0,
      "4008": 0,
      "5001": 0,
      "5002": 0,
      "5003": 0,
      "5004": 0,
      "5005": 0,
      "5006": 0,
      "5007": 0,
      "5008": 0,
      "6001": 0,
      "6002": 0,
      "6003": 0,
      "6004": 0,
      "6005": 0,
      "6006": 0,
      "6007": 0,
      "6008": 0,
      "7001": 0,
      "7002": 0,
      "7003": 0,
      "7004": 0,
      "7005": 0,
      "7006": 0,
      "7007": 0,
      "7008": 0
    },
    "Participant": 2,
    "Kickoff": {
      "Team": 1
    },
    "Parti1State": {},
    "Parti2State": {}
  },
  {
    "FixtureId": 18241006,
    "GameState": "scheduled",
    "StartTime": 1784142000000,
    "IsTeam": true,
    "FixtureGroupId": 10115573,
    "CompetitionId": 72,
    "CountryId": 466,
    "SportId": 1,
    "Participant1IsHome": true,
    "Participant2Id": 1489,
    "Participant1Id": 1888,
    "CoverageSecondaryData": true,
    "CoverageType": "TV/Stream",
    "Action": "goal_kick",
    "Id": 716,
    "Ts": 1784148291222,
    "ConnectionId": 1159,
    "Seq": 812,
    "StatusId": 4,
    "Type": "Soccer",
    "Clock": {
      "Running": true,
      "Seconds": 5023
    },
    "Stats": {
      "1": 1,
      "2": 0,
      "3": 1,
      "4": 2,
      "5": 0,
      "6": 0,
      "7": 1,
      "8": 5,
      "1001": 0,
      "1002": 0,
      "1003": 1,
      "1004": 1,
      "1005": 0,
      "1006": 0,
      "1007": 1,
      "1008": 1,
      "2001": 0,
      "2002": 0,
      "2003": 1,
      "2004": 1,
      "2005": 0,
      "2006": 0,
      "2007": 1,
      "2008": 1,
      "3001": 1,
      "3002": 0,
      "3003": 0,
      "3004": 1,
      "3005": 0,
      "3006": 0,
      "3007": 0,
      "3008": 4,
      "4001": 0,
      "4002": 0,
      "4003": 0,
      "4004": 0,
      "4005": 0,
      "4006": 0,
      "4007": 0,
      "4008": 0,
      "5001": 0,
      "5002": 0,
      "5003": 0,
      "5004": 0,
      "5005": 0,
      "5006": 0,
      "5007": 0,
      "5008": 0,
      "6001": 0,
      "6002": 0,
      "6003": 0,
      "6004": 0,
      "6005": 0,
      "6006": 0,
      "6007": 0,
      "6008": 0,
      "7001": 0,
      "7002": 0,
      "7003": 0,
      "7004": 0,
      "7005": 0,
      "7006": 0,
      "7007": 0,
      "7008": 0
    },
    "Participant": 1,
    "Possession": 1,
    "PossessionType": "SafePossession"
  },
  {
    "FixtureId": 18241006,
    "GameState": "scheduled",
    "StartTime": 1784142000000,
    "IsTeam": true,
    "FixtureGroupId": 10115573,
    "CompetitionId": 72,
    "CountryId": 466,
    "SportId": 1,
    "Participant1IsHome": true,
    "Participant2Id": 1489,
    "Participant1Id": 1888,
    "CoverageSecondaryData": true,
    "CoverageType": "TV/Stream",
    "Action": "halftime_finalised",
    "Id": 377,
    "Ts": 1784145044821,
    "ConnectionId": 1135,
    "Seq": 425,
    "StatusId": 3,
    "Score": {
      "Participant1": {
        "H1": {
          "YellowCards": 1,
          "Corners": 1
        },
        "HT": {
          "YellowCards": 1,
          "Corners": 1
        },
        "Total": {
          "YellowCards": 1,
          "Corners": 1
        }
      },
      "Participant2": {
        "H1": {
          "YellowCards": 1,
          "Corners": 1
        },
        "HT": {
          "YellowCards": 1,
          "Corners": 1
        },
        "Total": {
          "YellowCards": 1,
          "Corners": 1
        }
      }
    },
    "Stats": {
      "1": 0,
      "2": 0,
      "3": 1,
      "4": 1,
      "5": 0,
      "6": 0,
      "7": 1,
      "8": 1,
      "1001": 0,
      "1002": 0,
      "1003": 1,
      "1004": 1,
      "1005": 0,
      "1006": 0,
      "1007": 1,
      "1008": 1,
      "2001": 0,
      "2002": 0,
      "2003": 1,
      "2004": 1,
      "2005": 0,
      "2006": 0,
      "2007": 1,
      "2008": 1,
      "3001": 0,
      "3002": 0,
      "3003": 0,
      "3004": 0,
      "3005": 0,
      "3006": 0,
      "3007": 0,
      "3008": 0,
      "4001": 0,
      "4002": 0,
      "4003": 0,
      "4004": 0,
      "4005": 0,
      "4006": 0,
      "4007": 0,
      "4008": 0,
      "5001": 0,
      "5002": 0,
      "5003": 0,
      "5004": 0,
      "5005": 0,
      "5006": 0,
      "5007": 0,
      "5008": 0,
      "6001": 0,
      "6002": 0,
      "6003": 0,
      "6004": 0,
      "6005": 0,
      "6006": 0,
      "6007": 0,
      "6008": 0,
      "7001": 0,
      "7002": 0,
      "7003": 0,
      "7004": 0,
      "7005": 0,
      "7006": 0,
      "7007": 0,
      "7008": 0
    }
  },
  {
    "FixtureId": 18241006,
    "GameState": "scheduled",
    "StartTime": 1784142000000,
    "IsTeam": true,
    "FixtureGroupId": 10115573,
    "CompetitionId": 72,
    "CountryId": 466,
    "SportId": 1,
    "Participant1IsHome": true,
    "Participant2Id": 1489,
    "Participant1Id": 1888,
    "CoverageSecondaryData": true,
    "CoverageType": "TV/Stream",
    "Action": "high_danger_possession",
    "Id": 835,
    "Ts": 1784149329372,
    "ConnectionId": 1159,
    "Seq": 955,
    "StatusId": 4,
    "Type": "Soccer",
    "Clock": {
      "Running": true,
      "Seconds": 6061
    },
    "Stats": {
      "1": 1,
      "2": 2,
      "3": 1,
      "4": 3,
      "5": 0,
      "6": 0,
      "7": 1,
      "8": 6,
      "1001": 0,
      "1002": 0,
      "1003": 1,
      "1004": 1,
      "1005": 0,
      "1006": 0,
      "1007": 1,
      "1008": 1,
      "2001": 0,
      "2002": 0,
      "2003": 1,
      "2004": 1,
      "2005": 0,
      "2006": 0,
      "2007": 1,
      "2008": 1,
      "3001": 1,
      "3002": 2,
      "3003": 0,
      "3004": 2,
      "3005": 0,
      "3006": 0,
      "3007": 0,
      "3008": 5,
      "4001": 0,
      "4002": 0,
      "4003": 0,
      "4004": 0,
      "4005": 0,
      "4006": 0,
      "4007": 0,
      "4008": 0,
      "5001": 0,
      "5002": 0,
      "5003": 0,
      "5004": 0,
      "5005": 0,
      "5006": 0,
      "5007": 0,
      "5008": 0,
      "6001": 0,
      "6002": 0,
      "6003": 0,
      "6004": 0,
      "6005": 0,
      "6006": 0,
      "6007": 0,
      "6008": 0,
      "7001": 0,
      "7002": 0,
      "7003": 0,
      "7004": 0,
      "7005": 0,
      "7006": 0,
      "7007": 0,
      "7008": 0
    },
    "Participant": 1,
    "Possession": 1,
    "PossessionType": "HighDangerPossession"
  },
  {
    "FixtureId": 18241006,
    "GameState": "scheduled",
    "StartTime": 1784142000000,
    "IsTeam": true,
    "FixtureGroupId": 10115573,
    "CompetitionId": 72,
    "CountryId": 466,
    "SportId": 1,
    "Participant1IsHome": true,
    "Participant2Id": 1489,
    "Participant1Id": 1888,
    "CoverageSecondaryData": true,
    "CoverageType": "TV/Stream",
    "Action": "injury",
    "Id": 746,
    "Ts": 1784148666948,
    "ConnectionId": 1159,
    "Seq": 850,
    "StatusId": 4,
    "Type": "Soccer",
    "Confirmed": true,
    "Clock": {
      "Running": true,
      "Seconds": 5284
    },
    "Data": {
      "Outcome": "OffPitch",
      "Participant": 1,
      "PlayerId": 162605
    },
    "Stats": {
      "1": 1,
      "2": 1,
      "3": 1,
      "4": 2,
      "5": 0,
      "6": 0,
      "7": 1,
      "8": 6,
      "1001": 0,
      "1002": 0,
      "1003": 1,
      "1004": 1,
      "1005": 0,
      "1006": 0,
      "1007": 1,
      "1008": 1,
      "2001": 0,
      "2002": 0,
      "2003": 1,
      "2004": 1,
      "2005": 0,
      "2006": 0,
      "2007": 1,
      "2008": 1,
      "3001": 1,
      "3002": 1,
      "3003": 0,
      "3004": 1,
      "3005": 0,
      "3006": 0,
      "3007": 0,
      "3008": 5,
      "4001": 0,
      "4002": 0,
      "4003": 0,
      "4004": 0,
      "4005": 0,
      "4006": 0,
      "4007": 0,
      "4008": 0,
      "5001": 0,
      "5002": 0,
      "5003": 0,
      "5004": 0,
      "5005": 0,
      "5006": 0,
      "5007": 0,
      "5008": 0,
      "6001": 0,
      "6002": 0,
      "6003": 0,
      "6004": 0,
      "6005": 0,
      "6006": 0,
      "6007": 0,
      "6008": 0,
      "7001": 0,
      "7002": 0,
      "7003": 0,
      "7004": 0,
      "7005": 0,
      "7006": 0,
      "7007": 0,
      "7008": 0
    }
  },
  {
    "FixtureId": 18241006,
    "GameState": "scheduled",
    "StartTime": 1784142000000,
    "IsTeam": true,
    "FixtureGroupId": 10115573,
    "CompetitionId": 72,
    "CountryId": 466,
    "SportId": 1,
    "Participant1IsHome": true,
    "Participant2Id": 1489,
    "Participant1Id": 1888,
    "CoverageSecondaryData": true,
    "CoverageType": "TV/Stream",
    "Action": "jersey",
    "Id": 13,
    "Ts": 1784139523448,
    "ConnectionId": 1159,
    "Seq": 7,
    "StatusId": 1,
    "Type": "Soccer",
    "Clock": {
      "Running": false,
      "Seconds": 0
    },
    "Data": {
      "Color": "navyblue"
    },
    "Stats": {},
    "Participant": 2
  },
  {
    "FixtureId": 18241006,
    "GameState": "scheduled",
    "StartTime": 1784142000000,
    "IsTeam": true,
    "FixtureGroupId": 10115573,
    "CompetitionId": 72,
    "CountryId": 466,
    "SportId": 1,
    "Participant1IsHome": true,
    "Participant2Id": 1489,
    "Participant1Id": 1888,
    "CoverageSecondaryData": true,
    "CoverageType": "TV/Stream",
    "Action": "kickoff",
    "Id": 767,
    "Ts": 1784148900480,
    "ConnectionId": 1159,
    "Seq": 877,
    "StatusId": 4,
    "Type": "Soccer",
    "Confirmed": true,
    "Clock": {
      "Running": true,
      "Seconds": 5632
    },
    "Stats": {
      "1": 1,
      "2": 2,
      "3": 1,
      "4": 3,
      "5": 0,
      "6": 0,
      "7": 1,
      "8": 6,
      "1001": 0,
      "1002": 0,
      "1003": 1,
      "1004": 1,
      "1005": 0,
      "1006": 0,
      "1007": 1,
      "1008": 1,
      "2001": 0,
      "2002": 0,
      "2003": 1,
      "2004": 1,
      "2005": 0,
      "2006": 0,
      "2007": 1,
      "2008": 1,
      "3001": 1,
      "3002": 2,
      "3003": 0,
      "3004": 2,
      "3005": 0,
      "3006": 0,
      "3007": 0,
      "3008": 5,
      "4001": 0,
      "4002": 0,
      "4003": 0,
      "4004": 0,
      "4005": 0,
      "4006": 0,
      "4007": 0,
      "4008": 0,
      "5001": 0,
      "5002": 0,
      "5003": 0,
      "5004": 0,
      "5005": 0,
      "5006": 0,
      "5007": 0,
      "5008": 0,
      "6001": 0,
      "6002": 0,
      "6003": 0,
      "6004": 0,
      "6005": 0,
      "6006": 0,
      "6007": 0,
      "6008": 0,
      "7001": 0,
      "7002": 0,
      "7003": 0,
      "7004": 0,
      "7005": 0,
      "7006": 0,
      "7007": 0,
      "7008": 0
    },
    "Kickoff": {
      "Team": 1
    },
    "Possession": 1
  },
  {
    "FixtureId": 18241006,
    "GameState": "scheduled",
    "StartTime": 1784142000000,
    "IsTeam": true,
    "FixtureGroupId": 10115573,
    "CompetitionId": 72,
    "CountryId": 466,
    "SportId": 1,
    "Participant1IsHome": true,
    "Participant2Id": 1489,
    "Participant1Id": 1888,
    "CoverageSecondaryData": true,
    "CoverageType": "TV/Stream",
    "Action": "kickoff_team",
    "Id": 20,
    "Ts": 1784141962808,
    "ConnectionId": 1159,
    "Seq": 12,
    "StatusId": 1,
    "Type": "Soccer",
    "Confirmed": true,
    "Clock": {
      "Running": false,
      "Seconds": 0
    },
    "Stats": {},
    "Participant": 2,
    "Possession": 2
  },
  {
    "FixtureId": 18241006,
    "GameState": "scheduled",
    "StartTime": 1784142000000,
    "IsTeam": true,
    "FixtureGroupId": 10115573,
    "CompetitionId": 72,
    "CountryId": 466,
    "SportId": 1,
    "Participant1IsHome": true,
    "Participant2Id": 1489,
    "Participant1Id": 1888,
    "CoverageSecondaryData": true,
    "CoverageType": "TV/Stream",
    "Action": "lineups",
    "Id": 15,
    "Ts": 1784140127880,
    "ConnectionId": 1128,
    "Seq": 9,
    "Confirmed": true,
    "Stats": {},
    "Lineups": [
      {
        "id": "00000000-0000-0005-0000-000000000760",
        "normativeId": 1888,
        "preferredName": "England",
        "gender": "male",
        "updateDateMillis": 1721302980068,
        "lineups": [
          {
            "fixturePlayerId": 840742,
            "statusId": 0,
            "positionId": 36,
            "unitId": 0,
            "rosterNumber": "8",
            "starter": true,
            "starred": false,
            "player": {
              "id": "87953596-c77d-4b24-8d9a-a33e0833103c",
              "normativeId": 10015384,
              "country": "England",
              "team": "00000000-0000-0005-0000-00000000185a,00000000-0000-0005-0000-000000000a69,00000000-0000-0005-0000-000000000760,00000000-0000-0005-0000-0000000009d7",
              "dateOfBirth": "2002-11-06",
              "gender": "male",
              "preferredName": "Anderson, Elliot",
              "updateDateMillis": 1784070402899
            }
          },
          {
            "fixturePlayerId": 840743,
            "statusId": 0,
            "positionId": 36,
            "unitId": 0,
            "rosterNumber": "10",
            "starter": true,
            "starred": false,
            "player": {
              "id": "00000000-0000-0004-0000-00000011dbe3",
              "normativeId": 1170403,
              "country": "England",
              "team": "00000000-0000-0005-0000-000000000760,00000000-0000-0005-0000-000000000b1d",
              "dateOfBirth": "2003-06-29",
              "gender": "male",
              "preferredName": "Bellingham, Jude",
              "updateDateMillis": 1784070402900
            }
          },
          {
            "fixturePlayerId": 840744,
            "statusId": 0,
            "positionId": 35,
            "unitId": 0,
            "rosterNumber": "15",
            "starter": false,
            "starred": false,
            "player": {
              "id": "00000000-0000-0004-0000-00000002d99a",
              "normativeId": 186778,
              "country": "England",
              "team": "00000000-0000-0005-0000-000000000a4a,00000000-0000-0005-0000-000000000760",
              "dateOfBirth": "1992-05-09",
              "gender": "male",
              "preferredName": "Burn, Dan",
              "updateDateMillis": 1784070402875
            }
          },
          {
            "fixturePlayerId": 840745,
            "statusId": 0,
            "positionId": 35,
            "unitId": 0,
            "rosterNumber": "12",
            "starter": false,
            "starred": false,
            "player": {
              "id": "00000000-0000-0004-0000-0000000630b3",
              "normativeId": 405683,
              "country": "England",
              "team": "00000000-0000-0005-0000-0000000006b4,00000000-0000-0005-0000-000000000760",
              "dateOfBirth": "1999-07-05",
              "gender": "male",
              "preferredName": "Chalobah, Trevoh",
              "updateDateMillis": 1784070402900
            }
          },
          {
            "fixturePlayerId": 840748,
            "statusId": 0,
            "positionId": 36,
            "unitId": 0,
            "rosterNumber": "21",
            "starter": false,
            "starred": false,
            "player": {
              "id": "00000000-0000-0004-0000-0000000b017f",
              "normativeId": 721279,
              "country": "England",
              "team": "00000000-0000-0005-0000-000000000760,00000000-0000-0005-0000-0000000005da",
              "dateOfBirth": "1998-06-29",
              "gender": "male",
              "preferredName": "Eze, Eberechi",
              "updateDateMillis": 1784070402875
            }
          },
          {
            "fixturePlayerId": 840749,
            "statusId": 0,
            "positionId": 37,
            "unitId": 0,
            "rosterNumber": "18",
            "starter": true,
            "starred": false,
            "player": {
              "id": "00000000-0000-0004-0000-0000000de82c",
              "normativeId": 911404,
              "country": "England",
              "team": "00000000-0000-0005-0000-000000000760,00000000-0000-0005-0000-000000000610",
              "dateOfBirth": "2001-02-24",
              "gender": "male",
              "preferredName": "Gordon, Anthony",
              "updateDateMillis": 1784070402900
            }
          },
          {
            "fixturePlayerId": 840751,
            "statusId": 0,
            "positionId": 35,
            "unitId": 0,
            "rosterNumber": "6",
            "starter": true,
            "starred": false,
            "player": {
              "id": "00000000-0000-0004-0000-0000000d916e",
              "normativeId": 889198,
              "country": "England",
              "team": "00000000-0000-0005-0000-000000000760,00000000-0000-0005-0000-0000000009d7",
              "dateOfBirth": "2000-07-13",
              "gender": "male",
              "preferredName": "Guehi, Marc",
              "updateDateMillis": 1784070402900
            }
          },
          {
            "fixturePlayerId": 840752,
            "statusId": 0,
            "positionId": 34,
            "unitId": 0,
            "rosterNumber": "13",
            "starter": false,
            "starred": false,
            "player": {
              "id": "143a652b-a285-4015-a7d4-60c8cc77580a",
              "normativeId": 10095466,
              "country": "England",
              "team": "00000000-0000-0005-0000-0000000006eb,00000000-0000-0005-0000-000000000760",
              "dateOfBirth": "1997-03-12",
              "gender": "male",
              "preferredName": "Henderson, Dean",
              "updateDateMillis": 1784070402899
            }
          },
          {
            "fixturePlayerId": 840753,
            "statusId": 0,
            "positionId": 36,
            "unitId": 0,
            "rosterNumber": "14",
            "starter": false,
            "starred": false,
            "player": {
              "id": "00000000-0000-0004-0000-00000000be35",
              "normativeId": 48693,
              "country": "England",
              "team": "00000000-0000-0005-0000-000000000667,00000000-0000-0005-0000-000000000760",
              "dateOfBirth": "1990-06-17",
              "gender": "male",
              "preferredName": "Henderson, Jordan",
              "updateDateMillis": 1784070402877
            }
          },
          {
            "fixturePlayerId": 840754,
            "statusId": 0,
            "positionId": 35,
            "unitId": 0,
            "rosterNumber": "24",
            "starter": true,
            "starred": false,
            "player": {
              "id": "00000000-0000-0004-0000-0000000c05a8",
              "normativeId": 787880,
              "country": "England",
              "team": "00000000-0000-0005-0000-0000000006b4,00000000-0000-0005-0000-000000000760",
              "dateOfBirth": "1999-12-08",
              "gender": "male",
              "preferredName": "James, Reece (1999)",
              "updateDateMillis": 1784070402898
            }
          },
          {
            "fixturePlayerId": 840756,
            "statusId": 0,
            "positionId": 37,
            "unitId": 0,
            "rosterNumber": "9",
            "starter": true,
            "starred": false,
            "player": {
              "id": "00000000-0000-0004-0000-000000011351",
              "normativeId": 70481,
              "country": "England",
              "team": "00000000-0000-0005-0000-000000000760,00000000-0000-0005-0000-00000000061c",
              "dateOfBirth": "1993-07-28",
              "gender": "male",
              "preferredName": "Kane, Harry",
              "updateDateMillis": 1784070402876
            }
          },
          {
            "fixturePlayerId": 840758,
            "statusId": 0,
            "positionId": 35,
            "unitId": 0,
            "rosterNumber": "2",
            "starter": false,
            "starred": false,
            "player": {
              "id": "00000000-0000-0004-0000-000000094541",
              "normativeId": 607553,
              "country": "England",
              "team": "00000000-0000-0005-0000-000000000760,00000000-0000-0005-0000-0000000005e2",
              "dateOfBirth": "1997-10-23",
              "gender": "male",
              "preferredName": "Konsa Ngoyo, Ezri",
              "updateDateMillis": 1784070402899
            }
          },
          {
            "fixturePlayerId": 840761,
            "statusId": 0,
            "positionId": 37,
            "unitId": 0,
            "rosterNumber": "20",
            "starter": false,
            "starred": false,
            "player": {
              "id": "d7191d5e-0f24-4b86-8e9b-c522158287a7",
              "normativeId": 10096559,
              "country": "England",
              "team": "00000000-0000-0005-0000-00000000185a,00000000-0000-0005-0000-0000000005da,00000000-0000-0005-0000-000000000760",
              "dateOfBirth": "2002-03-10",
              "gender": "male",
              "preferredName": "Madueke, Chukwunonso",
              "updateDateMillis": 1784070402875
            }
          },
          {
            "fixturePlayerId": 840762,
            "statusId": 0,
            "positionId": 36,
            "unitId": 0,
            "rosterNumber": "16",
            "starter": false,
            "starred": false,
            "player": {
              "id": "0ba6136a-fea8-4b4b-84cf-3148766cbc4a",
              "normativeId": 10036773,
              "country": "England",
              "team": "00000000-0000-0005-0000-0000000009d8,00000000-0000-0005-0000-000000000760",
              "dateOfBirth": "2005-04-19",
              "gender": "male",
              "preferredName": "Mainoo, Kobbie",
              "updateDateMillis": 1784070402900
            }
          },
          {
            "fixturePlayerId": 840766,
            "statusId": 0,
            "positionId": 35,
            "unitId": 0,
            "rosterNumber": "3",
            "starter": false,
            "starred": false,
            "player": {
              "id": "6f1f23dc-7c4f-4121-b96c-4720667ef86b",
              "normativeId": 10194364,
              "country": "England",
              "team": "00000000-0000-0005-0000-0000000009d7,00000000-0000-0005-0000-000000000760",
              "dateOfBirth": "2005-03-21",
              "gender": "male",
              "preferredName": "O'Reilly, Nico",
              "updateDateMillis": 1784070402900
            }
          },
          {
            "fixturePlayerId": 840768,
            "statusId": 0,
            "positionId": 34,
            "unitId": 0,
            "rosterNumber": "1",
            "starter": true,
            "starred": false,
            "player": {
              "id": "00000000-0000-0004-0000-0000000f004f",
              "normativeId": 983119,
              "country": "England",
              "team": "00000000-0000-0005-0000-000000000760,00000000-0000-0005-0000-00000000077b",
              "dateOfBirth": "1994-03-07",
              "gender": "male",
              "preferredName": "Pickford, Jordan",
              "updateDateMillis": 1784070402876
            }
          },
          {
            "fixturePlayerId": 840769,
            "statusId": 1,
            "positionId": 35,
            "unitId": 0,
            "rosterNumber": "26",
            "starter": false,
            "starred": false,
            "player": {
              "id": "8f8b9a35-ee5b-40f2-a6e1-4c354e173429",
              "normativeId": 10095175,
              "country": "England",
              "team": "00000000-0000-0005-0000-00000000185a,00000000-0000-0005-0000-00000000097b,00000000-0000-0005-0000-000000000760",
              "dateOfBirth": "2003-01-29",
              "gender": "male",
              "preferredName": "Quansah, Jarell",
              "updateDateMillis": 1784070402900
            }
          },
          {
            "fixturePlayerId": 840770,
            "statusId": 0,
            "positionId": 37,
            "unitId": 0,
            "rosterNumber": "11",
            "starter": false,
            "starred": false,
            "player": {
              "id": "00000000-0000-0004-0000-000000090638",
              "normativeId": 591416,
              "country": "England",
              "team": "00000000-0000-0005-0000-000000000760",
              "dateOfBirth": "1997-10-31",
              "gender": "male",
              "preferredName": "Rashford, Marcus",
              "updateDateMillis": 1784070402899
            }
          },
          {
            "fixturePlayerId": 840771,
            "statusId": 0,
            "positionId": 36,
            "unitId": 0,
            "rosterNumber": "4",
            "starter": true,
            "starred": false,
            "player": {
              "id": "00000000-0000-0004-0000-0000000afcfa",
              "normativeId": 720122,
              "country": "England",
              "team": "00000000-0000-0005-0000-000000000760,00000000-0000-0005-0000-0000000005da",
              "dateOfBirth": "1999-01-14",
              "gender": "male",
              "preferredName": "Rice, Declan",
              "updateDateMillis": 1784070402899
            }
          },
          {
            "fixturePlayerId": 840772,
            "statusId": 0,
            "positionId": 36,
            "unitId": 0,
            "rosterNumber": "17",
            "starter": true,
            "starred": false,
            "player": {
              "id": "00000000-0000-0004-0000-0000000fbbb3",
              "normativeId": 1031091,
              "country": "England",
              "team": "00000000-0000-0005-0000-0000000005e2,00000000-0000-0005-0000-000000000760,00000000-0000-0005-0000-00000000185a",
              "dateOfBirth": "2002-07-26",
              "gender": "male",
              "preferredName": "Rogers, Morgan",
              "updateDateMillis": 1784070402899
            }
          },
          {
            "fixturePlayerId": 840773,
            "statusId": 0,
            "positionId": 37,
            "unitId": 0,
            "rosterNumber": "7",
            "starter": false,
            "starred": false,
            "player": {
              "id": "00000000-0000-0004-0000-0000001050ab",
              "normativeId": 1069227,
              "country": "England",
              "team": "00000000-0000-0005-0000-000000000760,00000000-0000-0005-0000-0000000005da",
              "dateOfBirth": "2001-09-05",
              "gender": "male",
              "preferredName": "Saka, Bukayo",
              "updateDateMillis": 1784070402900
            }
          },
          {
            "fixturePlayerId": 840774,
            "statusId": 0,
            "positionId": 35,
            "unitId": 0,
            "rosterNumber": "25",
            "starter": true,
            "starred": false,
            "player": {
              "id": "00000000-0000-0004-0000-0000000fba42",
              "normativeId": 1030722,
              "country": "England",
              "team": "00000000-0000-0005-0000-000000000c56,00000000-0000-0005-0000-000000000760",
              "dateOfBirth": "2000-08-09",
              "gender": "male",
              "preferredName": "Spence, Djed",
              "updateDateMillis": 1784070402877
            }
          },
          {
            "fixturePlayerId": 840775,
            "statusId": 0,
            "positionId": 35,
            "unitId": 0,
            "rosterNumber": "5",
            "starter": true,
            "starred": false,
            "player": {
              "id": "00000000-0000-0004-0000-000000027b2d",
              "normativeId": 162605,
              "country": "England",
              "team": "00000000-0000-0005-0000-0000000009d7,00000000-0000-0005-0000-000000000760",
              "dateOfBirth": "1994-05-28",
              "gender": "male",
              "preferredName": "Stones, John",
              "updateDateMillis": 1784070402875
            }
          },
          {
            "fixturePlayerId": 840777,
            "statusId": 0,
            "positionId": 37,
            "unitId": 0,
            "rosterNumber": "22",
            "starter": false,
            "starred": false,
            "player": {
              "id": "00000000-0000-0004-0000-00000002e54b",
              "normativeId": 189771,
              "country": "England",
              "team": "00000000-0000-0005-0000-000000002737,00000000-0000-0005-0000-000000000760",
              "dateOfBirth": "1996-03-16",
              "gender": "male",
              "preferredName": "Toney, Ivan",
              "updateDateMillis": 1784070402899
            }
          },
          {
            "fixturePlayerId": 840778,
            "statusId": 0,
            "positionId": 34,
            "unitId": 0,
            "rosterNumber": "23",
            "starter": false,
            "starred": false,
            "player": {
              "id": "f9220b09-f647-4c1c-8739-d069f0a12b0e",
              "normativeId": 10096978,
              "country": "England",
              "team": "00000000-0000-0005-0000-0000000009d7,00000000-0000-0005-0000-00000000185a,00000000-0000-0005-0000-000000000760",
              "dateOfBirth": "2002-10-10",
              "gender": "male",
              "preferredName": "Trafford, James",
              "updateDateMillis": 1784070402899
            }
          },
          {
            "fixturePlayerId": 840779,
            "statusId": 0,
            "positionId": 37,
            "unitId": 0,
            "rosterNumber": "19",
            "starter": false,
            "starred": false,
            "player": {
              "id": "00000000-0000-0004-0000-00000007990f",
              "normativeId": 497935,
              "country": "England",
              "team": "00000000-0000-0005-0000-0000000005e2,00000000-0000-0005-0000-000000000760",
              "dateOfBirth": "1995-12-30",
              "gender": "male",
              "preferredName": "Watkins, Ollie",
              "updateDateMillis": 1784070402898
            }
          }
        ]
      },
      {
        "id": "00000000-0000-0005-0000-0000000005d1",
        "normativeId": 1489,
        "preferredName": "Argentina",
        "gender": "male",
        "updateDateMillis": 1721301952519,
        "lineups": [
          {
            "fixturePlayerId": 840781,
            "statusId": 0,
            "positionId": 37,
            "unitId": 0,
            "rosterNumber": "16",
            "starter": false,
            "starred": false,
            "player": {
              "id": "c9b6b36a-d6b0-4729-ad3e-ae417e402db7",
              "normativeId": 10096940,
              "country": "Argentina",
              "team": "00000000-0000-0005-0000-0000000005d1,00000000-0000-0005-0000-0000000005e6",
              "dateOfBirth": "2001-04-26",
              "gender": "male",
              "preferredName": "Almada, Thiago",
              "updateDateMillis": 1784070074074
            }
          },
          {
            "fixturePlayerId": 840782,
            "statusId": 0,
            "positionId": 37,
            "unitId": 0,
            "rosterNumber": "9",
            "starter": true,
            "starred": false,
            "player": {
              "id": "00000000-0000-0004-0000-000000105db8",
              "normativeId": 1072568,
              "country": "Argentina",
              "team": "00000000-0000-0005-0000-0000000005d1,00000000-0000-0005-0000-0000000005e6",
              "dateOfBirth": "2000-01-31",
              "gender": "male",
              "preferredName": "Alvarez, Julian",
              "updateDateMillis": 1784070074076
            }
          },
          {
            "fixturePlayerId": 840784,
            "statusId": 1,
            "positionId": 35,
            "unitId": 0,
            "rosterNumber": "2",
            "starter": false,
            "starred": false,
            "player": {
              "id": "00000000-0000-0004-0000-0000001038c1",
              "normativeId": 1063105,
              "country": "Argentina",
              "team": "00000000-0000-0005-0000-0000000009e5,00000000-0000-0005-0000-0000000005d1",
              "dateOfBirth": "1999-01-26",
              "gender": "male",
              "preferredName": "Balerdi Rossa, Leonardo Julian",
              "updateDateMillis": 1784070074074
            }
          },
          {
            "fixturePlayerId": 840785,
            "statusId": 0,
            "positionId": 36,
            "unitId": 0,
            "rosterNumber": "8",
            "starter": false,
            "starred": false,
            "player": {
              "id": "0f44cdfd-eeec-4900-a683-2f65e8d65c3f",
              "normativeId": 10098924,
              "country": "Argentina",
              "team": "00000000-0000-0005-0000-0000000005d1,00000000-0000-0005-0000-000000000c07",
              "dateOfBirth": "2004-07-23",
              "gender": "male",
              "preferredName": "Barco, Valentin",
              "updateDateMillis": 1784070074075
            }
          },
          {
            "fixturePlayerId": 840792,
            "statusId": 0,
            "positionId": 36,
            "unitId": 0,
            "rosterNumber": "7",
            "starter": false,
            "starred": false,
            "player": {
              "id": "bc2effd9-597a-4604-8302-4fd36bb55462",
              "normativeId": 10093937,
              "country": "Argentina",
              "team": "00000000-0000-0005-0000-0000000005d1,00000000-0000-0005-0000-00000012c1d1",
              "dateOfBirth": "1994-05-24",
              "gender": "male",
              "preferredName": "De Paul, Rodrigo",
              "updateDateMillis": 1784070074074
            }
          },
          {
            "fixturePlayerId": 840800,
            "statusId": 0,
            "positionId": 36,
            "unitId": 0,
            "rosterNumber": "24",
            "starter": true,
            "starred": false,
            "player": {
              "id": "0a1f8497-fc76-4f9c-aa01-40b463f91596",
              "normativeId": 10035609,
              "country": "Argentina",
              "team": "00000000-0000-0005-0000-0000000006b4,00000000-0000-0005-0000-0000000005d1",
              "dateOfBirth": "2001-01-17",
              "gender": "male",
              "preferredName": "Fernandez, Enzo",
              "updateDateMillis": 1784070074074
            }
          },
          {
            "fixturePlayerId": 840803,
            "statusId": 0,
            "positionId": 37,
            "unitId": 0,
            "rosterNumber": "15",
            "starter": false,
            "starred": false,
            "player": {
              "id": "00000000-0000-0004-0000-0000000fad65",
              "normativeId": 1027429,
              "country": "Argentina",
              "team": "00000000-0000-0005-0000-0000000005d1",
              "dateOfBirth": "1998-04-06",
              "gender": "male",
              "preferredName": "Gonzalez, Nicolas Ivan",
              "updateDateMillis": 1784070074074
            }
          },
          {
            "fixturePlayerId": 840804,
            "statusId": 0,
            "positionId": 36,
            "unitId": 0,
            "rosterNumber": "11",
            "starter": false,
            "starred": false,
            "player": {
              "id": "00000000-0000-0004-0000-0000000a3061",
              "normativeId": 667745,
              "country": "Argentina",
              "team": "00000000-0000-0005-0000-000000000633,00000000-0000-0005-0000-0000000005d1",
              "dateOfBirth": "1996-04-09",
              "gender": "male",
              "preferredName": "Lo Celso, Giovani",
              "updateDateMillis": 1784070074076
            }
          },
          {
            "fixturePlayerId": 840805,
            "statusId": 0,
            "positionId": 37,
            "unitId": 0,
            "rosterNumber": "21",
            "starter": false,
            "starred": false,
            "player": {
              "id": "429d9cf9-9623-45d9-9582-7f84d76bb0cd",
              "normativeId": 10113696,
              "country": "Argentina",
              "team": "00000000-0000-0005-0000-000000000aab,00000000-0000-0005-0000-0000000005d1",
              "dateOfBirth": "2000-12-06",
              "gender": "male",
              "preferredName": "Lopez, Jose Manuel",
              "updateDateMillis": 1784070074075
            }
          },
          {
            "fixturePlayerId": 840806,
            "statusId": 0,
            "positionId": 36,
            "unitId": 0,
            "rosterNumber": "20",
            "starter": true,
            "starred": false,
            "player": {
              "id": "00000000-0000-0004-0000-000000121279",
              "normativeId": 1184377,
              "country": "Argentina",
              "team": "00000000-0000-0005-0000-000000000994,00000000-0000-0005-0000-0000000005d1",
              "dateOfBirth": "1998-12-24",
              "gender": "male",
              "preferredName": "Mac Allister, Alexis",
              "updateDateMillis": 1784070074076
            }
          },
          {
            "fixturePlayerId": 840807,
            "statusId": 0,
            "positionId": 34,
            "unitId": 0,
            "rosterNumber": "23",
            "starter": true,
            "starred": false,
            "player": {
              "id": "00000000-0000-0004-0000-000000080096",
              "normativeId": 524438,
              "country": "Argentina",
              "team": "00000000-0000-0005-0000-0000000005e2,00000000-0000-0005-0000-0000000005d1",
              "dateOfBirth": "1992-09-02",
              "gender": "male",
              "preferredName": "Martinez, Damian Emiliano",
              "updateDateMillis": 1784070074075
            }
          },
          {
            "fixturePlayerId": 840808,
            "statusId": 0,
            "positionId": 37,
            "unitId": 0,
            "rosterNumber": "22",
            "starter": false,
            "starred": false,
            "player": {
              "id": "00000000-0000-0004-0000-0000000e77c7",
              "normativeId": 948167,
              "country": "Argentina",
              "team": "00000000-0000-0005-0000-0000000008a8,00000000-0000-0005-0000-0000000005d1",
              "dateOfBirth": "1997-08-22",
              "gender": "male",
              "preferredName": "Martinez, Lautaro Javier",
              "updateDateMillis": 1784070074075
            }
          },
          {
            "fixturePlayerId": 840809,
            "statusId": 0,
            "positionId": 35,
            "unitId": 0,
            "rosterNumber": "6",
            "starter": true,
            "starred": false,
            "player": {
              "id": "00000000-0000-0004-0000-00000010d6c5",
              "normativeId": 1103557,
              "country": "Argentina",
              "team": "00000000-0000-0005-0000-0000000009d8,00000000-0000-0005-0000-0000000005d1",
              "dateOfBirth": "1998-01-18",
              "gender": "male",
              "preferredName": "Martinez, Lisandro",
              "updateDateMillis": 1784070074076
            }
          },
          {
            "fixturePlayerId": 840810,
            "statusId": 0,
            "positionId": 35,
            "unitId": 0,
            "rosterNumber": "25",
            "starter": false,
            "starred": false,
            "player": {
              "id": "a347b364-3102-4a43-aca5-6407c6076a84",
              "normativeId": 10092867,
              "country": "Argentina",
              "team": "00000000-0000-0005-0000-0000000009e5,00000000-0000-0005-0000-0000000005d1",
              "dateOfBirth": "1999-05-28",
              "gender": "male",
              "preferredName": "Medina, Facundo",
              "updateDateMillis": 1784070074074
            }
          },
          {
            "fixturePlayerId": 840811,
            "statusId": 0,
            "positionId": 37,
            "unitId": 0,
            "rosterNumber": "10",
            "starter": true,
            "starred": false,
            "player": {
              "id": "00000000-0000-0004-0000-00000000b5dd",
              "normativeId": 46557,
              "country": "Argentina",
              "team": "00000000-0000-0005-0000-0000000005d1,00000000-0000-0005-0000-00000012c1d1",
              "dateOfBirth": "1987-06-24",
              "gender": "male",
              "preferredName": "Messi, Lionel",
              "updateDateMillis": 1784070074075
            }
          },
          {
            "fixturePlayerId": 840812,
            "statusId": 0,
            "positionId": 35,
            "unitId": 0,
            "rosterNumber": "26",
            "starter": true,
            "starred": false,
            "player": {
              "id": "4692ac0e-0173-465a-8856-e01c89f8cfdf",
              "normativeId": 10093946,
              "country": "Argentina",
              "team": "00000000-0000-0005-0000-0000000005e6,00000000-0000-0005-0000-0000000005d1",
              "dateOfBirth": "1998-04-06",
              "gender": "male",
              "preferredName": "Molina Lucero, Nahuel",
              "updateDateMillis": 1784070074074
            }
          },
          {
            "fixturePlayerId": 840813,
            "statusId": 0,
            "positionId": 35,
            "unitId": 0,
            "rosterNumber": "4",
            "starter": false,
            "starred": false,
            "player": {
              "id": "00000000-0000-0004-0000-0000000d9fc8",
              "normativeId": 892872,
              "country": "Argentina",
              "team": "00000000-0000-0005-0000-000000000b2e,00000000-0000-0005-0000-0000000005d1",
              "dateOfBirth": "1997-01-01",
              "gender": "male",
              "preferredName": "Montiel, Gonzalo Ariel",
              "updateDateMillis": 1784070074075
            }
          },
          {
            "fixturePlayerId": 840814,
            "statusId": 0,
            "positionId": 34,
            "unitId": 0,
            "rosterNumber": "1",
            "starter": false,
            "starred": false,
            "player": {
              "id": "00000000-0000-0004-0000-000000080a0e",
              "normativeId": 526862,
              "country": "Argentina",
              "team": "00000000-0000-0005-0000-0000000005e6,00000000-0000-0005-0000-0000000005d1",
              "dateOfBirth": "1994-05-06",
              "gender": "male",
              "preferredName": "Musso, Juan Agustin",
              "updateDateMillis": 1784070074074
            }
          },
          {
            "fixturePlayerId": 840815,
            "statusId": 0,
            "positionId": 35,
            "unitId": 0,
            "rosterNumber": "19",
            "starter": false,
            "starred": false,
            "player": {
              "id": "00000000-0000-0004-0000-00000000b761",
              "normativeId": 46945,
              "country": "Argentina",
              "team": "00000000-0000-0005-0000-0000000005d1,00000000-0000-0005-0000-000000000b2e",
              "dateOfBirth": "1988-02-12",
              "gender": "male",
              "preferredName": "Otamendi, Nicolas",
              "updateDateMillis": 1784070074076
            }
          },
          {
            "fixturePlayerId": 840816,
            "statusId": 0,
            "positionId": 36,
            "unitId": 0,
            "rosterNumber": "14",
            "starter": false,
            "starred": false,
            "player": {
              "id": "00000000-0000-0004-0000-000000071d31",
              "normativeId": 466225,
              "country": "Argentina",
              "team": "00000000-0000-0005-0000-00000000097b,00000000-0000-0005-0000-0000000005d1",
              "dateOfBirth": "1998-10-05",
              "gender": "male",
              "preferredName": "Palacios, Exequiel",
              "updateDateMillis": 1784070074075
            }
          },
          {
            "fixturePlayerId": 840817,
            "statusId": 0,
            "positionId": 36,
            "unitId": 0,
            "rosterNumber": "5",
            "starter": true,
            "starred": false,
            "player": {
              "id": "00000000-0000-0004-0000-00000003684d",
              "normativeId": 223309,
              "country": "Argentina",
              "team": "00000000-0000-0005-0000-0000000005d1,00000000-0000-0005-0000-000000000646",
              "dateOfBirth": "1994-06-29",
              "gender": "male",
              "preferredName": "Paredes, Leandro",
              "updateDateMillis": 1784070074074
            }
          },
          {
            "fixturePlayerId": 840818,
            "statusId": 0,
            "positionId": 37,
            "unitId": 0,
            "rosterNumber": "18",
            "starter": false,
            "starred": false,
            "player": {
              "id": "f0ec2909-e6b8-475a-9e8b-f8726c5c77aa",
              "normativeId": 10093616,
              "country": "Argentina",
              "team": "00000000-0000-0005-0000-0000000006d8,00000000-0000-0005-0000-0000000005d1",
              "dateOfBirth": "2004-09-08",
              "gender": "male",
              "preferredName": "Paz Martinez, Nicolas",
              "updateDateMillis": 1784070074075
            }
          },
          {
            "fixturePlayerId": 840823,
            "statusId": 0,
            "positionId": 35,
            "unitId": 0,
            "rosterNumber": "13",
            "starter": true,
            "starred": false,
            "player": {
              "id": "00000000-0000-0004-0000-000000101a7c",
              "normativeId": 1055356,
              "country": "Argentina",
              "team": "00000000-0000-0005-0000-000000000c56,00000000-0000-0005-0000-0000000005d1",
              "dateOfBirth": "1998-04-27",
              "gender": "male",
              "preferredName": "Romero, Cristian Gabriel",
              "updateDateMillis": 1784070074075
            }
          },
          {
            "fixturePlayerId": 840825,
            "statusId": 0,
            "positionId": 34,
            "unitId": 0,
            "rosterNumber": "12",
            "starter": false,
            "starred": false,
            "player": {
              "id": "00000000-0000-0004-0000-00000008246b",
              "normativeId": 533611,
              "country": "Argentina",
              "team": "00000000-0000-0005-0000-0000000005d1,00000000-0000-0005-0000-0000000009e5",
              "dateOfBirth": "1992-05-20",
              "gender": "male",
              "preferredName": "Rulli, Geronimo",
              "updateDateMillis": 1784070074075
            }
          },
          {
            "fixturePlayerId": 840826,
            "statusId": 0,
            "positionId": 35,
            "unitId": 0,
            "rosterNumber": "2",
            "starter": false,
            "starred": false,
            "player": {
              "id": "00000000-0000-0004-0000-000000122324",
              "normativeId": 1188644,
              "country": "Argentina",
              "team": "00000000-0000-0005-0000-0000000005d1,00000000-0000-0005-0000-000000000c56",
              "dateOfBirth": "1997-05-10",
              "gender": "male",
              "preferredName": "Senesi, Marcos",
              "updateDateMillis": 1784070074075
            }
          },
          {
            "fixturePlayerId": 840828,
            "statusId": 0,
            "positionId": 37,
            "unitId": 0,
            "rosterNumber": "17",
            "starter": true,
            "starred": false,
            "player": {
              "id": "293383f6-5070-4d7a-a761-fa6184f3f35b",
              "normativeId": 10093427,
              "country": "Argentina",
              "team": "00000000-0000-0005-0000-0000000005e6,00000000-0000-0005-0000-0000000005d1",
              "dateOfBirth": "2002-12-18",
              "gender": "male",
              "preferredName": "Simeone, Giuliano",
              "updateDateMillis": 1784070074075
            }
          },
          {
            "fixturePlayerId": 840830,
            "statusId": 0,
            "positionId": 35,
            "unitId": 0,
            "rosterNumber": "3",
            "starter": true,
            "starred": false,
            "player": {
              "id": "426b7849-3e84-4e8c-bec3-abf6252e3b9c",
              "normativeId": 10092897,
              "country": "Argentina",
              "team": "00000000-0000-0005-0000-0000000009c0,00000000-0000-0005-0000-0000000005d1",
              "dateOfBirth": "1992-08-31",
              "gender": "male",
              "preferredName": "Tagliafico, Nicolas Alejandro",
              "updateDateMillis": 1784070074074
            }
          }
        ]
      }
    ]
  },
  {
    "FixtureId": 18241006,
    "GameState": "scheduled",
    "StartTime": 1784142000000,
    "IsTeam": true,
    "FixtureGroupId": 10115573,
    "CompetitionId": 72,
    "CountryId": 466,
    "SportId": 1,
    "Participant1IsHome": true,
    "Participant2Id": 1489,
    "Participant1Id": 1888,
    "CoverageSecondaryData": true,
    "CoverageType": "TV/Stream",
    "Action": "pitch",
    "Id": 10,
    "Ts": 1784139516513,
    "ConnectionId": 1159,
    "Seq": 4,
    "StatusId": 1,
    "Type": "Soccer",
    "Clock": {
      "Running": false,
      "Seconds": 0
    },
    "Data": {
      "Conditions": [
        "Good"
      ]
    },
    "Stats": {}
  },
  {
    "FixtureId": 18241006,
    "GameState": "scheduled",
    "StartTime": 1784142000000,
    "IsTeam": true,
    "FixtureGroupId": 10115573,
    "CompetitionId": 72,
    "CountryId": 466,
    "SportId": 1,
    "Participant1IsHome": true,
    "Participant2Id": 1489,
    "Participant1Id": 1888,
    "CoverageSecondaryData": true,
    "CoverageType": "TV/Stream",
    "Action": "players_on_the_pitch",
    "Id": 19,
    "Ts": 1784141532091,
    "ConnectionId": 1159,
    "Seq": 11,
    "StatusId": 1,
    "Type": "Soccer",
    "Confirmed": true,
    "Clock": {
      "Running": false,
      "Seconds": 0
    },
    "Stats": {}
  },
  {
    "FixtureId": 18241006,
    "GameState": "scheduled",
    "StartTime": 1784142000000,
    "IsTeam": true,
    "FixtureGroupId": 10115573,
    "CompetitionId": 72,
    "CountryId": 466,
    "SportId": 1,
    "Participant1IsHome": true,
    "Participant2Id": 1489,
    "Participant1Id": 1888,
    "CoverageSecondaryData": true,
    "CoverageType": "TV/Stream",
    "Action": "players_warming_up",
    "Id": 18,
    "Ts": 1784141243182,
    "ConnectionId": 1159,
    "Seq": 10,
    "StatusId": 1,
    "Type": "Soccer",
    "Confirmed": true,
    "Clock": {
      "Running": false,
      "Seconds": 0
    },
    "Stats": {}
  },
  {
    "FixtureId": 18241006,
    "GameState": "scheduled",
    "StartTime": 1784142000000,
    "IsTeam": true,
    "FixtureGroupId": 10115573,
    "CompetitionId": 72,
    "CountryId": 466,
    "SportId": 1,
    "Participant1IsHome": true,
    "Participant2Id": 1489,
    "Participant1Id": 1888,
    "CoverageSecondaryData": true,
    "CoverageType": "TV/Stream",
    "Action": "possession",
    "Id": 828,
    "Ts": 1784149283383,
    "ConnectionId": 1159,
    "Seq": 947,
    "StatusId": 4,
    "Type": "Soccer",
    "Clock": {
      "Running": true,
      "Seconds": 6015
    },
    "Stats": {
      "1": 1,
      "2": 2,
      "3": 1,
      "4": 3,
      "5": 0,
      "6": 0,
      "7": 1,
      "8": 6,
      "1001": 0,
      "1002": 0,
      "1003": 1,
      "1004": 1,
      "1005": 0,
      "1006": 0,
      "1007": 1,
      "1008": 1,
      "2001": 0,
      "2002": 0,
      "2003": 1,
      "2004": 1,
      "2005": 0,
      "2006": 0,
      "2007": 1,
      "2008": 1,
      "3001": 1,
      "3002": 2,
      "3003": 0,
      "3004": 2,
      "3005": 0,
      "3006": 0,
      "3007": 0,
      "3008": 5,
      "4001": 0,
      "4002": 0,
      "4003": 0,
      "4004": 0,
      "4005": 0,
      "4006": 0,
      "4007": 0,
      "4008": 0,
      "5001": 0,
      "5002": 0,
      "5003": 0,
      "5004": 0,
      "5005": 0,
      "5006": 0,
      "5007": 0,
      "5008": 0,
      "6001": 0,
      "6002": 0,
      "6003": 0,
      "6004": 0,
      "6005": 0,
      "6006": 0,
      "6007": 0,
      "6008": 0,
      "7001": 0,
      "7002": 0,
      "7003": 0,
      "7004": 0,
      "7005": 0,
      "7006": 0,
      "7007": 0,
      "7008": 0
    },
    "Participant": 1,
    "Possession": 1
  },
  {
    "FixtureId": 18241006,
    "GameState": "scheduled",
    "StartTime": 1784142000000,
    "IsTeam": true,
    "FixtureGroupId": 10115573,
    "CompetitionId": 72,
    "CountryId": 466,
    "SportId": 1,
    "Participant1IsHome": true,
    "Participant2Id": 1489,
    "Participant1Id": 1888,
    "CoverageSecondaryData": true,
    "CoverageType": "TV/Stream",
    "Action": "possible",
    "Id": 731,
    "Ts": 1784148469314,
    "ConnectionId": 1159,
    "Seq": 830,
    "StatusId": 4,
    "Type": "Soccer",
    "Clock": {
      "Running": true,
      "Seconds": 5201
    },
    "Data": {
      "RedCard": false,
      "YellowCard": false,
      "VAR": false
    },
    "Stats": {
      "1": 1,
      "2": 0,
      "3": 1,
      "4": 2,
      "5": 0,
      "6": 0,
      "7": 1,
      "8": 6,
      "1001": 0,
      "1002": 0,
      "1003": 1,
      "1004": 1,
      "1005": 0,
      "1006": 0,
      "1007": 1,
      "1008": 1,
      "2001": 0,
      "2002": 0,
      "2003": 1,
      "2004": 1,
      "2005": 0,
      "2006": 0,
      "2007": 1,
      "2008": 1,
      "3001": 1,
      "3002": 0,
      "3003": 0,
      "3004": 1,
      "3005": 0,
      "3006": 0,
      "3007": 0,
      "3008": 5,
      "4001": 0,
      "4002": 0,
      "4003": 0,
      "4004": 0,
      "4005": 0,
      "4006": 0,
      "4007": 0,
      "4008": 0,
      "5001": 0,
      "5002": 0,
      "5003": 0,
      "5004": 0,
      "5005": 0,
      "5006": 0,
      "5007": 0,
      "5008": 0,
      "6001": 0,
      "6002": 0,
      "6003": 0,
      "6004": 0,
      "6005": 0,
      "6006": 0,
      "6007": 0,
      "6008": 0,
      "7001": 0,
      "7002": 0,
      "7003": 0,
      "7004": 0,
      "7005": 0,
      "7006": 0,
      "7007": 0,
      "7008": 0
    },
    "Parti1State": {},
    "Parti2State": {},
    "PossibleEvent": {}
  },
  {
    "FixtureId": 18241006,
    "GameState": "scheduled",
    "StartTime": 1784142000000,
    "IsTeam": true,
    "FixtureGroupId": 10115573,
    "CompetitionId": 72,
    "CountryId": 466,
    "SportId": 1,
    "Participant1IsHome": true,
    "Participant2Id": 1489,
    "Participant1Id": 1888,
    "CoverageSecondaryData": true,
    "CoverageType": "TV/Stream",
    "Action": "safe_possession",
    "Id": 833,
    "Ts": 1784149319772,
    "ConnectionId": 1159,
    "Seq": 953,
    "StatusId": 4,
    "Type": "Soccer",
    "Clock": {
      "Running": true,
      "Seconds": 6051
    },
    "Stats": {
      "1": 1,
      "2": 2,
      "3": 1,
      "4": 3,
      "5": 0,
      "6": 0,
      "7": 1,
      "8": 6,
      "1001": 0,
      "1002": 0,
      "1003": 1,
      "1004": 1,
      "1005": 0,
      "1006": 0,
      "1007": 1,
      "1008": 1,
      "2001": 0,
      "2002": 0,
      "2003": 1,
      "2004": 1,
      "2005": 0,
      "2006": 0,
      "2007": 1,
      "2008": 1,
      "3001": 1,
      "3002": 2,
      "3003": 0,
      "3004": 2,
      "3005": 0,
      "3006": 0,
      "3007": 0,
      "3008": 5,
      "4001": 0,
      "4002": 0,
      "4003": 0,
      "4004": 0,
      "4005": 0,
      "4006": 0,
      "4007": 0,
      "4008": 0,
      "5001": 0,
      "5002": 0,
      "5003": 0,
      "5004": 0,
      "5005": 0,
      "5006": 0,
      "5007": 0,
      "5008": 0,
      "6001": 0,
      "6002": 0,
      "6003": 0,
      "6004": 0,
      "6005": 0,
      "6006": 0,
      "6007": 0,
      "6008": 0,
      "7001": 0,
      "7002": 0,
      "7003": 0,
      "7004": 0,
      "7005": 0,
      "7006": 0,
      "7007": 0,
      "7008": 0
    },
    "Participant": 1,
    "Possession": 1,
    "PossessionType": "SafePossession"
  },
  {
    "FixtureId": 18241006,
    "GameState": "scheduled",
    "StartTime": 1784142000000,
    "IsTeam": true,
    "FixtureGroupId": 10115573,
    "CompetitionId": 72,
    "CountryId": 466,
    "SportId": 1,
    "Participant1IsHome": true,
    "Participant2Id": 1489,
    "Participant1Id": 1888,
    "CoverageSecondaryData": true,
    "CoverageType": "TV/Stream",
    "Action": "shot",
    "Id": 761,
    "Ts": 1784148747704,
    "ConnectionId": 1159,
    "Seq": 867,
    "StatusId": 4,
    "Type": "Soccer",
    "Confirmed": true,
    "Clock": {
      "Running": true,
      "Seconds": 5478
    },
    "Data": {
      "Outcome": "Woodwork"
    },
    "Stats": {
      "1": 1,
      "2": 1,
      "3": 1,
      "4": 2,
      "5": 0,
      "6": 0,
      "7": 1,
      "8": 6,
      "1001": 0,
      "1002": 0,
      "1003": 1,
      "1004": 1,
      "1005": 0,
      "1006": 0,
      "1007": 1,
      "1008": 1,
      "2001": 0,
      "2002": 0,
      "2003": 1,
      "2004": 1,
      "2005": 0,
      "2006": 0,
      "2007": 1,
      "2008": 1,
      "3001": 1,
      "3002": 1,
      "3003": 0,
      "3004": 1,
      "3005": 0,
      "3006": 0,
      "3007": 0,
      "3008": 5,
      "4001": 0,
      "4002": 0,
      "4003": 0,
      "4004": 0,
      "4005": 0,
      "4006": 0,
      "4007": 0,
      "4008": 0,
      "5001": 0,
      "5002": 0,
      "5003": 0,
      "5004": 0,
      "5005": 0,
      "5006": 0,
      "5007": 0,
      "5008": 0,
      "6001": 0,
      "6002": 0,
      "6003": 0,
      "6004": 0,
      "6005": 0,
      "6006": 0,
      "6007": 0,
      "6008": 0,
      "7001": 0,
      "7002": 0,
      "7003": 0,
      "7004": 0,
      "7005": 0,
      "7006": 0,
      "7007": 0,
      "7008": 0
    },
    "Participant": 2
  },
  {
    "FixtureId": 18241006,
    "GameState": "scheduled",
    "StartTime": 1784142000000,
    "IsTeam": true,
    "FixtureGroupId": 10115573,
    "CompetitionId": 72,
    "CountryId": 466,
    "SportId": 1,
    "Participant1IsHome": true,
    "Participant2Id": 1489,
    "Participant1Id": 1888,
    "CoverageSecondaryData": true,
    "CoverageType": "TV/Stream",
    "Action": "standby",
    "Id": 766,
    "Ts": 1784148899206,
    "ConnectionId": 1159,
    "Seq": 876,
    "StatusId": 4,
    "Type": "Soccer",
    "Confirmed": true,
    "Clock": {
      "Running": true,
      "Seconds": 5617
    },
    "Stats": {
      "1": 1,
      "2": 2,
      "3": 1,
      "4": 3,
      "5": 0,
      "6": 0,
      "7": 1,
      "8": 6,
      "1001": 0,
      "1002": 0,
      "1003": 1,
      "1004": 1,
      "1005": 0,
      "1006": 0,
      "1007": 1,
      "1008": 1,
      "2001": 0,
      "2002": 0,
      "2003": 1,
      "2004": 1,
      "2005": 0,
      "2006": 0,
      "2007": 1,
      "2008": 1,
      "3001": 1,
      "3002": 2,
      "3003": 0,
      "3004": 2,
      "3005": 0,
      "3006": 0,
      "3007": 0,
      "3008": 5,
      "4001": 0,
      "4002": 0,
      "4003": 0,
      "4004": 0,
      "4005": 0,
      "4006": 0,
      "4007": 0,
      "4008": 0,
      "5001": 0,
      "5002": 0,
      "5003": 0,
      "5004": 0,
      "5005": 0,
      "5006": 0,
      "5007": 0,
      "5008": 0,
      "6001": 0,
      "6002": 0,
      "6003": 0,
      "6004": 0,
      "6005": 0,
      "6006": 0,
      "6007": 0,
      "6008": 0,
      "7001": 0,
      "7002": 0,
      "7003": 0,
      "7004": 0,
      "7005": 0,
      "7006": 0,
      "7007": 0,
      "7008": 0
    }
  },
  {
    "FixtureId": 18241006,
    "GameState": "scheduled",
    "StartTime": 1784142000000,
    "IsTeam": true,
    "FixtureGroupId": 10115573,
    "CompetitionId": 72,
    "CountryId": 466,
    "SportId": 1,
    "Participant1IsHome": true,
    "Participant2Id": 1489,
    "Participant1Id": 1888,
    "CoverageSecondaryData": true,
    "CoverageType": "TV/Stream",
    "Action": "status",
    "Id": 838,
    "Ts": 1784149378047,
    "ConnectionId": 1159,
    "Seq": 959,
    "StatusId": 5,
    "Type": "Soccer",
    "Data": {
      "StatusId": 5
    },
    "Stats": {
      "1": 1,
      "2": 2,
      "3": 1,
      "4": 3,
      "5": 0,
      "6": 0,
      "7": 1,
      "8": 6,
      "1001": 0,
      "1002": 0,
      "1003": 1,
      "1004": 1,
      "1005": 0,
      "1006": 0,
      "1007": 1,
      "1008": 1,
      "2001": 0,
      "2002": 0,
      "2003": 1,
      "2004": 1,
      "2005": 0,
      "2006": 0,
      "2007": 1,
      "2008": 1,
      "3001": 1,
      "3002": 2,
      "3003": 0,
      "3004": 2,
      "3005": 0,
      "3006": 0,
      "3007": 0,
      "3008": 5,
      "4001": 0,
      "4002": 0,
      "4003": 0,
      "4004": 0,
      "4005": 0,
      "4006": 0,
      "4007": 0,
      "4008": 0,
      "5001": 0,
      "5002": 0,
      "5003": 0,
      "5004": 0,
      "5005": 0,
      "5006": 0,
      "5007": 0,
      "5008": 0,
      "6001": 0,
      "6002": 0,
      "6003": 0,
      "6004": 0,
      "6005": 0,
      "6006": 0,
      "6007": 0,
      "6008": 0,
      "7001": 0,
      "7002": 0,
      "7003": 0,
      "7004": 0,
      "7005": 0,
      "7006": 0,
      "7007": 0,
      "7008": 0
    },
    "Kickoff": {
      "Team": 2
    },
    "PossessionType": "SafePossession"
  },
  {
    "FixtureId": 18241006,
    "GameState": "scheduled",
    "StartTime": 1784142000000,
    "IsTeam": true,
    "FixtureGroupId": 10115573,
    "CompetitionId": 72,
    "CountryId": 466,
    "SportId": 1,
    "Participant1IsHome": true,
    "Participant2Id": 1489,
    "Participant1Id": 1888,
    "CoverageSecondaryData": true,
    "CoverageType": "TV/Stream",
    "Action": "substitution",
    "Id": 780,
    "Ts": 1784148987314,
    "ConnectionId": 1159,
    "Seq": 894,
    "StatusId": 4,
    "Type": "Soccer",
    "Confirmed": true,
    "Clock": {
      "Running": true,
      "Seconds": 5719
    },
    "Data": {
      "Participant": 1,
      "PlayerInId": 189771,
      "PlayerOutId": 1030722
    },
    "Stats": {
      "1": 1,
      "2": 2,
      "3": 1,
      "4": 3,
      "5": 0,
      "6": 0,
      "7": 1,
      "8": 6,
      "1001": 0,
      "1002": 0,
      "1003": 1,
      "1004": 1,
      "1005": 0,
      "1006": 0,
      "1007": 1,
      "1008": 1,
      "2001": 0,
      "2002": 0,
      "2003": 1,
      "2004": 1,
      "2005": 0,
      "2006": 0,
      "2007": 1,
      "2008": 1,
      "3001": 1,
      "3002": 2,
      "3003": 0,
      "3004": 2,
      "3005": 0,
      "3006": 0,
      "3007": 0,
      "3008": 5,
      "4001": 0,
      "4002": 0,
      "4003": 0,
      "4004": 0,
      "4005": 0,
      "4006": 0,
      "4007": 0,
      "4008": 0,
      "5001": 0,
      "5002": 0,
      "5003": 0,
      "5004": 0,
      "5005": 0,
      "5006": 0,
      "5007": 0,
      "5008": 0,
      "6001": 0,
      "6002": 0,
      "6003": 0,
      "6004": 0,
      "6005": 0,
      "6006": 0,
      "6007": 0,
      "6008": 0,
      "7001": 0,
      "7002": 0,
      "7003": 0,
      "7004": 0,
      "7005": 0,
      "7006": 0,
      "7007": 0,
      "7008": 0
    }
  },
  {
    "FixtureId": 18241006,
    "GameState": "scheduled",
    "StartTime": 1784142000000,
    "IsTeam": true,
    "FixtureGroupId": 10115573,
    "CompetitionId": 72,
    "CountryId": 466,
    "SportId": 1,
    "Participant1IsHome": true,
    "Participant2Id": 1489,
    "Participant1Id": 1888,
    "CoverageSecondaryData": true,
    "CoverageType": "TV/Stream",
    "Action": "suspend",
    "Id": 398,
    "Ts": 1784146023990,
    "ConnectionId": 1129,
    "Seq": 447,
    "Confirmed": true,
    "Data": {},
    "Stats": {
      "1": 0,
      "2": 0,
      "3": 1,
      "4": 1,
      "5": 0,
      "6": 0,
      "7": 1,
      "8": 1,
      "1001": 0,
      "1002": 0,
      "1003": 1,
      "1004": 1,
      "1005": 0,
      "1006": 0,
      "1007": 1,
      "1008": 1,
      "2001": 0,
      "2002": 0,
      "2003": 1,
      "2004": 1,
      "2005": 0,
      "2006": 0,
      "2007": 1,
      "2008": 1,
      "3001": 0,
      "3002": 0,
      "3003": 0,
      "3004": 0,
      "3005": 0,
      "3006": 0,
      "3007": 0,
      "3008": 0,
      "4001": 0,
      "4002": 0,
      "4003": 0,
      "4004": 0,
      "4005": 0,
      "4006": 0,
      "4007": 0,
      "4008": 0,
      "5001": 0,
      "5002": 0,
      "5003": 0,
      "5004": 0,
      "5005": 0,
      "5006": 0,
      "5007": 0,
      "5008": 0,
      "6001": 0,
      "6002": 0,
      "6003": 0,
      "6004": 0,
      "6005": 0,
      "6006": 0,
      "6007": 0,
      "6008": 0,
      "7001": 0,
      "7002": 0,
      "7003": 0,
      "7004": 0,
      "7005": 0,
      "7006": 0,
      "7007": 0,
      "7008": 0
    }
  },
  {
    "FixtureId": 18241006,
    "GameState": "scheduled",
    "StartTime": 1784142000000,
    "IsTeam": true,
    "FixtureGroupId": 10115573,
    "CompetitionId": 72,
    "CountryId": 466,
    "SportId": 1,
    "Participant1IsHome": true,
    "Participant2Id": 1489,
    "Participant1Id": 1888,
    "CoverageSecondaryData": true,
    "CoverageType": "TV/Stream",
    "Action": "throw_in",
    "Id": 831,
    "Ts": 1784149304006,
    "ConnectionId": 1159,
    "Seq": 951,
    "StatusId": 4,
    "Type": "Soccer",
    "Confirmed": true,
    "Clock": {
      "Running": true,
      "Seconds": 6032
    },
    "Data": {
      "ThrowInType": "Attack"
    },
    "Stats": {
      "1": 1,
      "2": 2,
      "3": 1,
      "4": 3,
      "5": 0,
      "6": 0,
      "7": 1,
      "8": 6,
      "1001": 0,
      "1002": 0,
      "1003": 1,
      "1004": 1,
      "1005": 0,
      "1006": 0,
      "1007": 1,
      "1008": 1,
      "2001": 0,
      "2002": 0,
      "2003": 1,
      "2004": 1,
      "2005": 0,
      "2006": 0,
      "2007": 1,
      "2008": 1,
      "3001": 1,
      "3002": 2,
      "3003": 0,
      "3004": 2,
      "3005": 0,
      "3006": 0,
      "3007": 0,
      "3008": 5,
      "4001": 0,
      "4002": 0,
      "4003": 0,
      "4004": 0,
      "4005": 0,
      "4006": 0,
      "4007": 0,
      "4008": 0,
      "5001": 0,
      "5002": 0,
      "5003": 0,
      "5004": 0,
      "5005": 0,
      "5006": 0,
      "5007": 0,
      "5008": 0,
      "6001": 0,
      "6002": 0,
      "6003": 0,
      "6004": 0,
      "6005": 0,
      "6006": 0,
      "6007": 0,
      "6008": 0,
      "7001": 0,
      "7002": 0,
      "7003": 0,
      "7004": 0,
      "7005": 0,
      "7006": 0,
      "7007": 0,
      "7008": 0
    },
    "Participant": 1,
    "Possession": 1
  },
  {
    "FixtureId": 18241006,
    "GameState": "scheduled",
    "StartTime": 1784142000000,
    "IsTeam": true,
    "FixtureGroupId": 10115573,
    "CompetitionId": 72,
    "CountryId": 466,
    "SportId": 1,
    "Participant1IsHome": true,
    "Participant2Id": 1489,
    "Participant1Id": 1888,
    "CoverageSecondaryData": true,
    "CoverageType": "TV/Stream",
    "Action": "venue",
    "Id": 8,
    "Ts": 1784139512944,
    "ConnectionId": 1159,
    "Seq": 3,
    "StatusId": 1,
    "Type": "Soccer",
    "Clock": {
      "Running": false,
      "Seconds": 0
    },
    "Data": {
      "Type": "neutral"
    },
    "Stats": {}
  },
  {
    "FixtureId": 18241006,
    "GameState": "scheduled",
    "StartTime": 1784142000000,
    "IsTeam": true,
    "FixtureGroupId": 10115573,
    "CompetitionId": 72,
    "CountryId": 466,
    "SportId": 1,
    "Participant1IsHome": true,
    "Participant2Id": 1489,
    "Participant1Id": 1888,
    "CoverageSecondaryData": true,
    "CoverageType": "TV/Stream",
    "Action": "weather",
    "Id": 11,
    "Ts": 1784139518098,
    "ConnectionId": 1159,
    "Seq": 5,
    "StatusId": 1,
    "Type": "Soccer",
    "Clock": {
      "Running": false,
      "Seconds": 0
    },
    "Data": {
      "Conditions": [
        "Day"
      ]
    },
    "Stats": {}
  },
  {
    "FixtureId": 18241006,
    "GameState": "scheduled",
    "StartTime": 1784142000000,
    "IsTeam": true,
    "FixtureGroupId": 10115573,
    "CompetitionId": 72,
    "CountryId": 466,
    "SportId": 1,
    "Participant1IsHome": true,
    "Participant2Id": 1489,
    "Participant1Id": 1888,
    "CoverageSecondaryData": true,
    "CoverageType": "TV/Stream",
    "Action": "yellow_card",
    "Id": 765,
    "Ts": 1784148893959,
    "ConnectionId": 1159,
    "Seq": 875,
    "StatusId": 4,
    "Type": "Soccer",
    "Confirmed": true,
    "Clock": {
      "Running": true,
      "Seconds": 5617
    },
    "Score": {
      "Participant1": {
        "H1": {
          "YellowCards": 1,
          "Corners": 1
        },
        "HT": {
          "YellowCards": 1,
          "Corners": 1
        },
        "H2": {
          "Goals": 1
        },
        "Total": {
          "Goals": 1,
          "YellowCards": 1,
          "Corners": 1
        }
      },
      "Participant2": {
        "H1": {
          "YellowCards": 1,
          "Corners": 1
        },
        "HT": {
          "YellowCards": 1,
          "Corners": 1
        },
        "H2": {
          "Goals": 2,
          "YellowCards": 2,
          "Corners": 5
        },
        "Total": {
          "Goals": 2,
          "YellowCards": 3,
          "Corners": 6
        }
      }
    },
    "Data": {
      "PlayerId": 10093937
    },
    "Stats": {
      "1": 1,
      "2": 2,
      "3": 1,
      "4": 3,
      "5": 0,
      "6": 0,
      "7": 1,
      "8": 6,
      "1001": 0,
      "1002": 0,
      "1003": 1,
      "1004": 1,
      "1005": 0,
      "1006": 0,
      "1007": 1,
      "1008": 1,
      "2001": 0,
      "2002": 0,
      "2003": 1,
      "2004": 1,
      "2005": 0,
      "2006": 0,
      "2007": 1,
      "2008": 1,
      "3001": 1,
      "3002": 2,
      "3003": 0,
      "3004": 2,
      "3005": 0,
      "3006": 0,
      "3007": 0,
      "3008": 5,
      "4001": 0,
      "4002": 0,
      "4003": 0,
      "4004": 0,
      "4005": 0,
      "4006": 0,
      "4007": 0,
      "4008": 0,
      "5001": 0,
      "5002": 0,
      "5003": 0,
      "5004": 0,
      "5005": 0,
      "5006": 0,
      "5007": 0,
      "5008": 0,
      "6001": 0,
      "6002": 0,
      "6003": 0,
      "6004": 0,
      "6005": 0,
      "6006": 0,
      "6007": 0,
      "6008": 0,
      "7001": 0,
      "7002": 0,
      "7003": 0,
      "7004": 0,
      "7005": 0,
      "7006": 0,
      "7007": 0,
      "7008": 0
    },
    "Participant": 2,
    "PossibleEvent": {}
  }
]